{"schemaVersion":1,"bookId":"gre-random","unitId":"word-list-02","title":"Word List 02","sectionId":"gre-core","sectionTitle":"核心词汇","pageStart":30,"pageEnd":41,"extractionMethod":"ocr","wordEntryCount":121,"duplicateEntryCount":35,"pages":[{"number":30,"blocks":[{"type":"title","text":"Word List 02"},{"type":"text","text":"词根/词缓预习表"},{"type":"text","text":"词根/词级含义"},{"type":"text","text":"例词及释义"},{"type":"text","text":"词根/词级含义"},{"type":"text","text":"例词及释义"},{"type":"entry","text":"gen","headword":"gen"},{"type":"text","text":"产生"},{"type":"text","text":"indigenous adj 土产的，本地的 audit"},{"type":"text","text":"听"},{"type":"text","text":"audition v试演"},{"type":"entry","text":"crep","headword":"crep"},{"type":"text","text":"破裂"},{"type":"text","text":"discrepancy n.差异，矛盾"},{"type":"text","text":"cub"},{"type":"text","text":"躺"},{"type":"text","text":"incubate v.孵卵；培养"},{"type":"entry","text":"hypo-","headword":"hypo-"},{"type":"text","text":"在下面 hypothesis n.假设，假说"},{"type":"text","text":"orium"},{"type":"text","text":"地方"},{"type":"text","text":"auditoriumn.观众席；礼堂"},{"type":"text","text":"生态"},{"type":"text","text":"ecosystemn.生态系统"},{"type":"text","text":"turb"},{"type":"text","text":"搅动"},{"type":"text","text":"turbid adj. 浑浊的"},{"type":"entry","text":"eco-","headword":"eco-"},{"type":"text","text":"跟随"},{"type":"text","text":"sequeln.续篇，续集"},{"type":"text","text":"mut"},{"type":"text","text":"改变"},{"type":"text","text":"immutable adj不可改变的"},{"type":"entry","text":"sequ","headword":"sequ"},{"type":"entry","text":"estranged","headword":"estranged"},{"type":"definition","text":"adj. 疏远的(no longer in contact with sb.)"},{"type":"text","text":"[r'streind3d]"},{"type":"note","text":"联想记忆：e+strange（陌生的）+d→变成陌生→疏远的"},{"type":"text","text":"通estrangement (n. 疏远)"},{"type":"entry","text":"canon","headword":"canon"},{"type":"definition","text":"n.经典，真作（the works that are genuine)"},{"type":"text","text":"[kaenan]"},{"type":"note","text":"联想记忆：can（能）+on（在上）→能放在桌面上的真家伙→经典，真作"},{"type":"entry","text":"discrepancy","headword":"discrepancy"},{"type":"definition","text":"n.差异，矛盾(lack of agreement; inconsistency)"},{"type":"text","text":"[drs'krepansi]"},{"type":"note","text":"园联想记忆：dis（分开）+crep（破裂）+ancy→裂开→矛盾"}]},{"number":31,"blocks":[{"type":"text","text":"<<<GRE词汇精选乱序版"},{"type":"entry","text":"garment","headword":"garment"},{"type":"definition","text":"n. 衣服(any article of clothing)"},{"type":"text","text":"['ga:rmant]"},{"type":"text","text":"wollen garments 毛衣"},{"type":"entry","text":"unidimensional","headword":"unidimensional"},{"type":"definition","text":"adj. —维的(one-dimensional)"},{"type":"text","text":"[ju:nrdar'menfanl]"},{"type":"note","text":"联想记忆：uni(单一)+dimensional(空间的）→一维的"},{"type":"entry","text":"presumption","headword":"presumption"},{"type":"definition","text":"n.放肆，做慢(presumptuous attitude or conduct)：假定(assumption)"},{"type":"text","text":"[u{duvz,ud]"},{"type":"text","text":"园来自presume（v.推测，认定）"},{"type":"text","text":"presumptive （adj假设的，很可能的）"},{"type":"entry","text":"spartan","headword":"spartan"},{"type":"text","text":"['spa:rtn]"},{"type":"text","text":"园来自Sparta（斯巴达），为希腊城邦，该地区的人以简朴、刻苦著称。"},{"type":"entry","text":"estimable","headword":"estimable"},{"type":"definition","text":"adj.值得尊敬的(worthy of great respect);可估计的(capable of being estimated)"},{"type":"text","text":"['estrmabl]"},{"type":"text","text":"图来自estimate（v估计：评价）"},{"type":"text","text":"hypothesis"},{"type":"entry","text":"platitudinous","headword":"platitudinous"},{"type":"text","text":"[plaetr'tu:danas]"},{"type":"text","text":"图 platitudinous remarks陈腐的言论"},{"type":"text","text":"导使巴料"},{"type":"text","text":"1+1*2"},{"type":"entry","text":"piety","headword":"piety"},{"type":"definition","text":"n.孝顺，孝敬[fidelity to natural obligations （as to parents)]：虔诚（religious"},{"type":"text","text":"['parati]"},{"type":"text","text":"devotion to God)"},{"type":"text","text":"Kjejnbeu peddjsuom Aau oaeyeq uepgonb ul passaudxe sem /jeic jjeu1"},{"type":"text","text":"devoutness"},{"type":"entry","text":"refractory","headword":"refractory"},{"type":"definition","text":"adj.倔强的，难管理的（stubborn,unmanageable)：(病）难治的（resistant to"},{"type":"text","text":"[rr'fraektari]"},{"type":"text","text":"treatment or cure)"},{"type":"note","text":"园词根记忆：re（往回）+fract（断裂）+ory→宁折不弯→倔强的"},{"type":"entry","text":"vitriolic","headword":"vitriolic"},{"type":"definition","text":"adj. 刻薄的(virulent of feeling or of speech)"},{"type":"text","text":"[vitri'a:lik]"},{"type":"note","text":"圆词根记忆：vitri（玻璃，引申为“刻薄”）+olic→刻薄的"},{"type":"text","text":"Although a few delegates gave the opposition's suggestions a vitriolic"},{"type":"text","text":"response, most greeted the staitement of a counterposition with civility."},{"type":"entry","text":"sectarian","headword":"sectarian"},{"type":"definition","text":"adj. 教派的(of, relating to, or characteristic of a sect)"},{"type":"text","text":"[sek'terian]"},{"type":"note","text":"词根记忆：sect（切）+arian(的）→切开→搞宗派→宗派的"},{"type":"entry","text":"bludgeon","headword":"bludgeon"},{"type":"definition","text":"vt （尤指通过争解）追使(to overcome,often by intimidation or coercion）：用重"},{"type":"text","text":"[ueSpviq.]"},{"type":"text","text":"器连击(某人)(to hit with a heavy club or similar blunt instrument)"}]},{"number":32,"blocks":[{"type":"title","text":"Word List 02 >>>"},{"type":"text","text":"Exotic insect pests can produce both short- and long-term effects on forest"},{"type":"text","text":"ecosystems,"},{"type":"entry","text":"alarmist","headword":"alarmist"},{"type":"definition","text":"adj危言耸听的：骇人的(causing unnecessary fear and anxiety)"},{"type":"text","text":"[a'la:rmrst]"},{"type":"text","text":"园来自alarm（n.警报）"},{"type":"text","text":"alarmism（n.危言耸听：大惊小怪）"},{"type":"entry","text":"disconcert","headword":"disconcert"},{"type":"definition","text":"v.使不安，使困感，使尴尬（to make someone feel anxious，confused or"},{"type":"text","text":"[drskan's3:rt]"},{"type":"text","text":"embarrassed)"},{"type":"note","text":"圆词根记忆：dis（不）+con（表加强）+cert（搞清）没有搞清楚→使困惑"},{"type":"text","text":"abash"},{"type":"text","text":"disconcerting（adj.令人不安的：令人困感的：令人尴尬的）"},{"type":"entry","text":"sequel","headword":"sequel"},{"type":"definition","text":"n. 续篇，续集(a book, film that continues the story of an earlier one)"},{"type":"text","text":"['si:kwal]"},{"type":"note","text":"园词根记忆：sequ（跟随）+el→续篇"},{"type":"entry","text":"parsimonious","headword":"parsimonious"},{"type":"definition","text":"adj. 吝的(exhibiting or marked by parsimony)"},{"type":"text","text":"[parrst'maunias]"},{"type":"text","text":"国来自parsimony（n.各音）"},{"type":"text","text":"mingy, miserly, penurious, stingy, stinting, tightfisted, ungenerous"},{"type":"entry","text":"standstill","headword":"standstill"},{"type":"definition","text":"n.停止，停滞（stop）"},{"type":"text","text":"['staendstil]"},{"type":"entry","text":"methanol","headword":"methanol"},{"type":"definition","text":"n. 甲醇 (a poisonous form of alcohol formed when methane reacts with oxygen)"},{"type":"text","text":"['meBans:l]"},{"type":"text","text":"Methanol’s most attractive feature, however, is that it can reduce by about"},{"type":"title","text":"90 percent the vehicle emissions that form ozone, the most serious urban air"},{"type":"text","text":"pollutant."},{"type":"entry","text":"panegyric","headword":"panegyric"},{"type":"definition","text":"n. 领词(a eulogistic oration or writing)"},{"type":"text","text":"[paenadzrik]"},{"type":"note","text":"园词根记忆：pan（全部）+egyric（广场，集会）→公共集会的庆祝辞→领词"},{"type":"text","text":"eulogium, eulogy, hymn, paean"},{"type":"entry","text":"clueless","headword":"clueless"},{"type":"definition","text":"adj. 很愚套的(very stupid);不懂的(not able to understand or to do something.)"},{"type":"text","text":"[klu:las]"},{"type":"note","text":"圆词根记忆：clue（线索）+less（无-的）→没有线索的→不懂的"},{"type":"entry","text":"preachy","headword":"preachy"},{"type":"definition","text":"adj. x试B的(trying to give advice or to persuade)"},{"type":"text","text":"['pri:tfi]"},{"type":"text","text":"homiletic, moralistic, sententious"},{"type":"entry","text":"roil","headword":"roil"},{"type":"definition","text":"v. 抛浑(to make turbulent or muddy or cloudy by stirring up sediment); 使混乱L(to"},{"type":"text","text":"[jrc]"},{"type":"text","text":"cause to be in a state of agitation or disorder)"},{"type":"text","text":"disarray. disorder, disrupt, disturb, muddle"},{"type":"entry","text":"audition","headword":"audition"},{"type":"definition","text":"v试演(to take part in a trial performance)：让(某人)试演(to evaluate in a trial"},{"type":"text","text":"[ufxp,c]"},{"type":"text","text":"performance)"},{"type":"note","text":"园词根记忆：audit（听）+ion→昕（演员）试演→让（某人）试演"},{"type":"entry","text":"solace","headword":"solace"},{"type":"definition","text":"n.安慰：慰籍（comfort ingrief)"},{"type":"text","text":"['sa:las]"},{"type":"text","text":"consolation, relief"}]},{"number":33,"blocks":[{"type":"entry","text":"auditorium","headword":"auditorium"},{"type":"definition","text":"n. 观众席;礼堂(a room, hall, or building used for public gatherings)"},{"type":"text","text":"[ueu:c],1p:c']"},{"type":"note","text":"词根记忆：audit（听）+orium（地方）→听的地方→观众席，礼堂"},{"type":"entry","text":"disaffected","headword":"disaffected"},{"type":"definition","text":"adj. 不满的(resentful and rebellious, especially against authority)"},{"type":"text","text":"[,drsa'fektid]"},{"type":"note","text":"园词根记忆：dis（不，非）+affect（感情，情感）+ed→不好的感情→不满的"},{"type":"text","text":"disgruntled"},{"type":"text","text":"disaffection (n.不满)"},{"type":"entry","text":"minuscule","headword":"minuscule"},{"type":"definition","text":"adj. 极小的(extremely small)"},{"type":"text","text":"['minaskju:l]"},{"type":"note","text":"图词根记忆：minus（较小的）+cul→极小的"},{"type":"text","text":"diminutive, minuscule"},{"type":"entry","text":"gambit","headword":"gambit"},{"type":"definition","text":"n.开局：开场白(a remark intended to start a conversation or make a telling"},{"type":"text","text":"['gambrt]"},{"type":"text","text":"point)"},{"type":"entry","text":"turbid","headword":"turbid"},{"type":"definition","text":"adj. 浑浊的(deficient in clarity or purity)"},{"type":"text","text":"['t3:rbid]"},{"type":"note","text":"图词根记忆：turb（搅动）+id（有性质的）→搅动的→混浊的"},{"type":"text","text":"muddy"},{"type":"entry","text":"ascertain","headword":"ascertain"},{"type":"definition","text":"v.查明：弄清(to find out or learn with certainty)"},{"type":"text","text":"[esar'tein]"},{"type":"note","text":"图词根记忆：as（表加强）+cert（搞清）+ain→弄清，查明"},{"type":"entry","text":"pedantic","headword":"pedantic"},{"type":"definition","text":"adj. 学究气的(of, relating to, or being a pedant)"},{"type":"text","text":"[pr'daentrk]"},{"type":"text","text":"圆来自pedant（n.学究）。在莎士比亚时代，人们用pedant指学校的男老师，但是"},{"type":"text","text":"到16世纪末，pedant已经演变为专指卖弄细枝末节学问的人。"},{"type":"entry","text":"counterpoint","headword":"counterpoint"},{"type":"definition","text":"n. 对t比(use of contrasting elements in a work of art)"},{"type":"text","text":"[kauntarpornt]"},{"type":"text","text":"园组合词：counter（反对）+point（点）→与之相对的观点→对比"},{"type":"text","text":"Many critics of Emily Bronte's novel Wuthering Heights see its second part"},{"type":"text","text":"as a counterpoint that comments on, if it does not reverse, the first part, where a"},{"type":"text","text":"romantic reading receives more confirmation."},{"type":"entry","text":"unmistakable","headword":"unmistakable"},{"type":"definition","text":"adj. 清楚明白的(obvious);确定无疑的(that cannot be mistaken for sb./sth.else)"},{"type":"text","text":"[Anmr'sterkabl]"},{"type":"note","text":"联想记忆：un（没有）+mistak（ex错误）+able（能…·的）→能够确定没有错误的→确"},{"type":"text","text":"定无疑的"},{"type":"text","text":"decisive"}]},{"number":34,"blocks":[{"type":"title","text":"Word List 02 >>>"},{"type":"entry","text":"untoward","headword":"untoward"},{"type":"text","text":"adlj. 不良的(not favorable);不幸的(unlucky);棘手的(dificult to guide, manage,"},{"type":"text","text":"[p:C1,uv]"},{"type":"text","text":"or work with); 异常:的(unusual and unexpected)"},{"type":"note","text":"词根记忆：un（反）+to（朝向）+ward（表方向）→朝着相反的方向→异常的"},{"type":"entry","text":"perceptible","headword":"perceptible"},{"type":"definition","text":"adj. 可察觉的(capable of being perceived by the senses or the mind)"},{"type":"text","text":"[par'septabl]"},{"type":"note","text":"园词根记忆：per（完全）+cept（拿）+ible→完全拿捏的→可察觉的"},{"type":"text","text":"appreciable, apprehensible, detectable, discernible, distinguishable,"},{"type":"text","text":"palpable"},{"type":"entry","text":"churn","headword":"churn"},{"type":"definition","text":"v. 剧烈揽动(to stir or agitate violently)"},{"type":"text","text":"[t[3:rn]"},{"type":"entry","text":"flummery","headword":"flummery"},{"type":"definition","text":"n. 虚假的恭维(meaningless or deceptive language);废话(nonsense)"},{"type":"text","text":"[flamari]"},{"type":"text","text":"The starsd attitudes toward their glowing press are diametrically opposed:"},{"type":"text","text":"some think it flumrmery and others take the adulation seriously."},{"type":"entry","text":"emulsify","headword":"emulsify"},{"type":"definition","text":"v. (使)乳化(to make into an emulsion)"},{"type":"text","text":"[r'mAlsrfax]"},{"type":"note","text":"图词根记忆：ex（出）+mul（挤奶）+sify→乳化"},{"type":"entry","text":"malady","headword":"malady"},{"type":"definition","text":"n. 疾病(a disease or disorder of the animall body)"},{"type":"text","text":"['maeladi]"},{"type":"entry","text":"cryptography","headword":"cryptography"},{"type":"definition","text":"n.密码学;密码术(any of various mathematical techniques for encrypting"},{"type":"text","text":"[krip'ta:grafi]"},{"type":"text","text":"and decrypting data in order to keep it private when transmitted or stored"},{"type":"text","text":"electronically)"},{"type":"note","text":"圆词根记忆：crypto（隐藏）+graphy（写，记录）→隐藏的记录→密码学"},{"type":"entry","text":"didacticism","headword":"didacticism"},{"type":"definition","text":"n. 说教(communication that is suitable for or intended to be instructive)"},{"type":"note","text":"园词根记忆：didact（教）+ic+ism（主义，观点）→说教"},{"type":"text","text":"[dar'daktasizam]"},{"type":"entry","text":"valorize","headword":"valorize"},{"type":"definition","text":"v.规定价格，稳定物价(to establish.and maintain the price by governmental"},{"type":"text","text":"['vaelararz]"},{"type":"text","text":"action);认为 有价值(to think or state that something has value)"},{"type":"entry","text":"clownish","headword":"clownish"},{"type":"definition","text":"adj 小丑似的，傻的(silly)"},{"type":"text","text":"[klaunrj]"},{"type":"text","text":"图来自clown（n.小丑）"},{"type":"entry","text":"hodgepodge","headword":"hodgepodge"},{"type":"definition","text":"n. 大杂会(a mixture of dissimilar ingredients)"},{"type":"text","text":"['ha:d3pa:d3]"},{"type":"text","text":"patchwork, welter, pastiche"},{"type":"entry","text":"zeal","headword":"zeal"},{"type":"definition","text":"n. 热情，激情(enthusiastic devotion to a cause, ideal, or goal)"},{"type":"text","text":"[zi:l]"},{"type":"text","text":"fervor"},{"type":"text","text":"zealous（adj.热情的）"}]},{"number":35,"blocks":[{"type":"text","text":"<<<GRE词汇精选乱序版"},{"type":"entry","text":"suffice","headword":"suffice"},{"type":"definition","text":"v. 有能力(to be competent or capable);足以(be sufficient)"},{"type":"text","text":"[sa'fars]"},{"type":"note","text":"词根记忆：suf（下）+fic（做）+e→在下面先做好充足准备→充足"},{"type":"entry","text":"threshold","headword":"threshold"},{"type":"definition","text":"n. 界限, 临界点(the point that must be exceeded to begin producing a given"},{"type":"text","text":"['erefhauld]"},{"type":"text","text":"effect or result)"},{"type":"text","text":"3 As Permian life-forms declined, they reached a fatal rhresholc and species"},{"type":"text","text":"succumbed to mass extinction."},{"type":"entry","text":"proclivity","headword":"proclivity"},{"type":"definition","text":"n. 倾向(an inclination or predisposition toward sth.)"},{"type":"text","text":"[pra’klrvati]"},{"type":"text","text":"leaning"},{"type":"entry","text":"supplant","headword":"supplant"},{"type":"definition","text":"v. 排挤，取代(to supersede by force or treachery)"},{"type":"text","text":"[sa'plaent]"},{"type":"note","text":"词根记忆：sup（下面）+plant(种植）→在下面种植→排挤，取代"},{"type":"text","text":"When railroads first began to supplant rivers and canals as highways of"},{"type":"text","text":"commerce, they were regarded as blessings and their promoters were looked"},{"type":"text","text":"upon as benefactors."},{"type":"entry","text":"presuppose","headword":"presuppose"},{"type":"definition","text":"vt.预先假定（to suppose beforehand)：以-为先决条件(to require as an"},{"type":"text","text":"[zned,es:ud']"},{"type":"text","text":"antecedent in logic or fact)"},{"type":"entry","text":"succinct","headword":"succinct"},{"type":"definition","text":"adj 简明的，简洁的(marked by compact, precise expression)"},{"type":"text","text":"圈词根记忆：suc（下面）+cinct（看作gird，束起）→原指把下面的衣服束起来方便干"},{"type":"text","text":"[sak'sinkt]"},{"type":"text","text":"活→简洁的"},{"type":"text","text":"You should delete this paragraph in order to make your essay more succinct."},{"type":"text","text":"concise, compendiary, compendious, curt, laconic"},{"type":"entry","text":"hysteria","headword":"hysteria"},{"type":"text","text":"[hr'stria]"},{"type":"text","text":"(behavior exhibiting emotional excess)"},{"type":"note","text":"词根记忆：hyster（看作hystero，子宫；症）+ia→像患了癌症一样→歇斯底里症"},{"type":"text","text":"During the Battle of Trafalgar, Admiral Nelson remained imperturbable and in"},{"type":"example","text":"full command of the situation in spite of the hysteria and panic all around him."},{"type":"entry","text":"inverse","headword":"inverse"},{"type":"text","text":"adlj. 相反的(directly opposite);倒转的(inverted)"},{"type":"text","text":"[In'v3:rs]"},{"type":"text","text":"国词根记忆：in（反）+vers（转）+e→反转→相反的：倒转的"},{"type":"entry","text":"boon","headword":"boon"},{"type":"definition","text":"n.思惠，天照福利(a timely blessing or benefit)"},{"type":"text","text":"[bu:n]"},{"type":"note","text":"联想记忆：从月亮（moon）得到恩惠（boon）→天赐福利"},{"type":"text","text":"beaboonto对来说大有神益"},{"type":"entry","text":"transcend","headword":"transcend"},{"type":"definition","text":"v.超出，超越，胜过(to rise above or go beyond the limit)"},{"type":"text","text":"[traen'send]"},{"type":"text","text":"国词根记忆：trans（超过）+（s）cend（爬）→爬过→超越"},{"type":"entry","text":"retaliate","headword":"retaliate"},{"type":"definition","text":"v.报复，反击（to get revenge)"},{"type":"text","text":"[rr'taliert]"},{"type":"note","text":"园词根记忆：re（往回）+tali（那恶）+ate→把邪恶还回去→报复"},{"type":"entry","text":"insight","headword":"insight"},{"type":"definition","text":"n. 洞察力(the power or act of seeing into a situation);洞悉"},{"type":"text","text":"['rnsart]"},{"type":"note","text":"园词根记忆：in（进入）+sight（眼光）→眼光刺入→洞察力"},{"type":"text","text":"discernment, intuition, penetration, perception"},{"type":"entry","text":"perilous","headword":"perilous"},{"type":"definition","text":"adj危险的，冒险的(full of peril; hazardous)"},{"type":"text","text":"['peralas]"},{"type":"text","text":"来自peril(n.危险）"},{"type":"entry","text":"repudiate","headword":"repudiate"},{"type":"definition","text":"v.拒绝接受，回绝，抛弃（torefuse to accept）"}]},{"number":36,"blocks":[{"type":"title","text":"Word List 02 >>>"},{"type":"text","text":"Fashion is partly a search for a new language to discredit the old, a way in"},{"type":"text","text":"which each generaition can repudliate its immedliate predecessor and distinguish"},{"type":"text","text":"itself."},{"type":"text","text":"dismiss, reprobate, spurn"},{"type":"entry","text":"zealot","headword":"zealot"},{"type":"definition","text":"n. 狂热者(a zealous person)"},{"type":"text","text":"bigot, enthusiast, fanatic"},{"type":"text","text":"['zelat]"},{"type":"entry","text":"unqualified","headword":"unqualified"},{"type":"definition","text":"adj无资格的，不合格的（not having suitable qualifications)：无限制的，绝对的"},{"type":"text","text":"[An'kwa:lrfard]"},{"type":"text","text":"(not limited)"},{"type":"entry","text":"outmoded","headword":"outmoded"},{"type":"definition","text":"adj. 过时的(no longer in fashion; obsolete)"},{"type":"text","text":"[aut'maudid]"},{"type":"note","text":"园词根记忆：out（出）+mode（时尚）+d→不再时尚的→过时的"},{"type":"entry","text":"inherent","headword":"inherent"},{"type":"definition","text":"adj. 固有的，内在的(involved in the constitution or essential character of sth.:;"},{"type":"text","text":"[rn'hirant]"},{"type":"text","text":"belonging by nature or habit)"},{"type":"note","text":"词根记忆：in（向内）+her（黏附）+ent→黏附在内的→固有的，内在的"},{"type":"text","text":"be inherent in为.·-所固有"},{"type":"entry","text":"eradicate","headword":"eradicate"},{"type":"definition","text":"v. 根除(to tear out by the roots; uproot): 扑灭(to exterminate)"},{"type":"text","text":"[r'radrkert]"},{"type":"note","text":"园词根记忆：e（出）+radic（根）+ate→根除"},{"type":"text","text":"abolish, annihilate, extirpate"},{"type":"entry","text":"galvanize","headword":"galvanize"},{"type":"definition","text":"v. 刺激， 激起(to stimulate) ; 电(to plate metal with zinc, originally by galvanic"},{"type":"text","text":"[’gaelvanarz]"},{"type":"text","text":"action); 通电(to apply an electric current to)"},{"type":"text","text":"来自galvanic（adj电流的）"},{"type":"entry","text":"finicky","headword":"finicky"},{"type":"definition","text":"adj苛求的，过分讲究的（too particular or exacting:fussy)"},{"type":"note","text":"词根记忆：fin（fine，精细的）+icky→精细的→过分讲究的"},{"type":"text","text":"[finrki]"},{"type":"text","text":"dainty, fastidious, finicking"},{"type":"entry","text":"insipid","headword":"insipid"},{"type":"definition","text":"adj.乏味的，枯燥的(banal, dull, vapid)"},{"type":"text","text":"[in'sipid]"},{"type":"note","text":"圆词根记忆：in（不）+sip（有味道）+id→没味道的→乏味的"},{"type":"text","text":"Just as an insipic dish lacks flavor, an inane remark lacks sense."},{"type":"text","text":"distasteful, savorless, unappetizing. unpalatable, unsavory"},{"type":"entry","text":"evenhanded","headword":"evenhanded"},{"type":"definition","text":"adj.公平的，不偏不倚的（fair and impartial)"},{"type":"text","text":"[irvn'haendid]"},{"type":"note","text":"园联想记忆：even（平的）+hand（手）+ed→两手放得一样平→公平的"},{"type":"entry","text":"cursory","headword":"cursory"},{"type":"definition","text":"adj粗略的（superficial)：草率的(hasty)"},{"type":"text","text":"['ks:rsari]"},{"type":"note","text":"词根记忆：curs（跑）+ory→匆忙地跑过去→草率的"},{"type":"definition","text":"A cursory glance pays little attention to details."}]},{"number":37,"blocks":[{"type":"entry","text":"judicious","headword":"judicious"},{"type":"text","text":"(injeeo pue asm) :(jueu5pn[ punos Bumous jo Buyeu)编[ (pe"},{"type":"text","text":"[d3u'dx{as]"},{"type":"text","text":"国词根记忆：jud（判断）+icious→有判断力的"},{"type":"text","text":"judgmatic, prudent, sane, sapient, sensible"},{"type":"entry","text":"witty","headword":"witty"},{"type":"definition","text":"adj. 机智的(having good intellectual capacity); 风趣的(marked by or full of wit)"},{"type":"text","text":"[wrti]"},{"type":"entry","text":"reassure","headword":"reassure"},{"type":"definition","text":"v.使恢复信心（torestore to confidence）;使确信(to reinsure)"},{"type":"text","text":"[ri:a'fur]"},{"type":"note","text":"图词根记忆：re（一再）+assure（确信）一再确信→使恢复信心"},{"type":"entry","text":"adulation","headword":"adulation"},{"type":"definition","text":"n.奉承，追媚(excessive or slavish admiration or flattery)"},{"type":"text","text":"[ad3a'ler{n]"},{"type":"entry","text":"correlate","headword":"correlate"},{"type":"definition","text":"v.使相互关联：使相互影响(to establish a mutual or reciprocal relation)"},{"type":"text","text":"[ko:ralert]"},{"type":"text","text":"correlate...with...使..与...相互关联"},{"type":"entry","text":"deficiency","headword":"deficiency"},{"type":"definition","text":"n. 缺陷(absence of sth. essential; incompleteness); 不足(shortage)"},{"type":"text","text":"[drfrfnsi]"},{"type":"note","text":"园词根记忆：de（不）+fic（做）+iency→没做好→缺陷"},{"type":"entry","text":"utilitarian","headword":"utilitarian"},{"type":"definition","text":"adj. 功利的，实利的(exhibiting or preferring mere utility)"},{"type":"text","text":"[ju:trlr'terian]"},{"type":"text","text":"图 utilitarianism (n. 功利主义)"},{"type":"entry","text":"prolong","headword":"prolong"},{"type":"definition","text":"v延长，拉长(to lengthen)"},{"type":"text","text":"[pra'la:n]"},{"type":"text","text":"圈词根记忆：pro（向前）+long（长）→延长，拉长"},{"type":"text","text":"In their determination to discover ways to prolong human life, doctors fail to"},{"type":"text","text":"take into account that longer lives are not always happier ones."},{"type":"text","text":"elongate, extend, prolongate, protract"},{"type":"entry","text":"ingratiating","headword":"ingratiating"},{"type":"definition","text":"adj.讨人喜欢的，迷人的(capable of winning favor);讨好的，献媚的（calculated"},{"type":"text","text":"[rn'grerfiertrn]"},{"type":"text","text":"to please or win favor)"},{"type":"entry","text":"murky","headword":"murky"},{"type":"definition","text":"adj.黑暗的，昏暗的(dark, gloomy);朦胧的(vague)"},{"type":"text","text":"['m3:rki]"},{"type":"text","text":"国来自murk（n.黑暗，昏暗）"},{"type":"entry","text":"admonish","headword":"admonish"},{"type":"definition","text":"v. li诚(to reprove mildly); 警告(to warn, advise)"},{"type":"text","text":"[ad’ma:nx]"},{"type":"note","text":"圆词根记忆：ad（加强）+mon（警告）+ish→训诚；警告"}]},{"number":38,"blocks":[{"type":"title","text":"Word List 02 >>>"},{"type":"text","text":"Although he attempted repeatedlly to dlisabuse her of her conviction of his"},{"type":"text","text":"insincerity, he was not successful; she remained adamant in her judgment."},{"type":"entry","text":"relish","headword":"relish"},{"type":"definition","text":"n.美味，风味（pleasing flavor);喜好，兴趣（a strong liking)v喜好，享受（to be"},{"type":"text","text":"['relx]"},{"type":"text","text":"graltified by)"},{"type":"note","text":"联想记忆：rel(看作real，真正的）+ish（看作fish，鱼）→真正的鱼→美味"},{"type":"text","text":"Although I have always been confused by our transit system, I relish traveling"},{"type":"text","text":"on the subways occasionally"},{"type":"entry","text":"clerical","headword":"clerical"},{"type":"definition","text":"adj. 神职人员的(of, relating to, or characteristic of the clergy)"},{"type":"text","text":"['klerik]"},{"type":"note","text":"图联想记忆：和clergy（n.神职人员）一起记"},{"type":"definition","text":"n.基因组：染色体组(one haploid set of chromosomes with the genes they"},{"type":"entry","text":"alacrity","headword":"alacrity"},{"type":"definition","text":"n.欣然同意(cheerful wilingness; eagerness)"},{"type":"text","text":"[a'laekrati]"},{"type":"note","text":"图词根记忆：alacri（愉快的）+ty→欣然同意：十分乐意"},{"type":"text","text":"willingness"},{"type":"entry","text":"inclusive","headword":"inclusive"},{"type":"definition","text":"adj 全部包括的(covering or intended to cover all items, costs, or services); 首末项"},{"type":"text","text":"[In'klu:sIv]"},{"type":"text","text":"包括在内的(including the stated limits or extremes)"},{"type":"text","text":"国来自include（v包含）"},{"type":"text","text":"generic"},{"type":"text","text":"inclusiveness（n.包容：包容性）"},{"type":"entry","text":"cartography","headword":"cartography"},{"type":"definition","text":"n.制图，地图绘制（the science or art of making maps)"},{"type":"text","text":"[ka:r'ta:grafi]"},{"type":"note","text":"词根记忆：carto（图形）+graphy（画）→制图，制图学"},{"type":"text","text":"cartographer (n. 地图绘制员)"},{"type":"entry","text":"mummification","headword":"mummification"},{"type":"definition","text":"n. 木乃伊化(the process of preserving a dead body as a mummy)"},{"type":"text","text":"[mAmafa'ker{n]"},{"type":"note","text":"园词根记忆：mummi看作mummy，木乃伊）+fic（做）+ation→木乃伊化"},{"type":"text","text":"Although several ancient cultures practiced mummification, mummies from"},{"type":"text","text":"ancient Egypt are generally more well-preserved than mummies of similar"},{"type":"text","text":"antiquity from other cultures."}]},{"number":39,"blocks":[{"type":"entry","text":"convenience","headword":"convenience"},{"type":"definition","text":"n. 方便,便利(the quality of being useful, easy or suitable for someone)"},{"type":"text","text":"[kan'vi:nians]"},{"type":"text","text":"圈词根记忆：con（表加强）+ven（来）+ience（表状态）→全部能来，没有障碍→方便"},{"type":"text","text":"国convenient（adj附近的；近便的：容易到达的）"},{"type":"entry","text":"skeptic","headword":"skeptic"},{"type":"definition","text":"n. 怀疑论者 (a person who usually doubts that claims or statements are true)"},{"type":"text","text":"['skeptik]"},{"type":"note","text":"圆词根记忆：skept(怀疑）+ic（人)→怀疑论者"},{"type":"text","text":"skepticism（n.怀疑态度）"},{"type":"entry","text":"choreograph","headword":"choreograph"},{"type":"definition","text":"v. 编舞(to design the steps and movements for dancers); 设计, 筹划(to arrange"},{"type":"text","text":"['ko:riagraf]"},{"type":"text","text":"or direct the progress, or details of)"},{"type":"note","text":"园词根记忆：choreo（看作chor，舞）+graph（写）+y→编舞"},{"type":"entry","text":"marginal","headword":"marginal"},{"type":"text","text":"o o)更 (uogns jo dno5 uodu jo uj e jo you) (p"},{"type":"text","text":"[ma:rd3inl]"},{"type":"text","text":"central importance)"},{"type":"text","text":"园来自margin（n.页边，边缘）"},{"type":"text","text":"peripheral"},{"type":"entry","text":"sham","headword":"sham"},{"type":"definition","text":"n. 假象(something false or empty that is purported to be genuine); 虚伪"},{"type":"text","text":"[{aem]"},{"type":"text","text":"(deceitfulness or pretense)"},{"type":"entry","text":"censor","headword":"censor"},{"type":"definition","text":"n.审查员，审查官（an official who examines materials)v.审查（to examine)"},{"type":"text","text":"['sensar]"},{"type":"note","text":"园词根记忆：cens（审查）+or（人）→审查员"},{"type":"text","text":"censorship（n.审查：检查：审查制度）"},{"type":"entry","text":"desperate","headword":"desperate"},{"type":"definition","text":"adj. 绝望的(having lost hope)"},{"type":"text","text":"['desparat]"},{"type":"note","text":"词根记忆：de（离开）+sper（希望）+ate(的）→希望离开→绝望的"},{"type":"text","text":"despondent"},{"type":"text","text":"desperation (n. 绝望)"},{"type":"entry","text":"release","headword":"release"},{"type":"definition","text":"v. 释放(to set free from restraint, confinement, or servitude); 解雇(to let go);解"},{"type":"text","text":"[r'li:s]"},{"type":"text","text":"除 (to set free from obligations, commitments, or debt)"},{"type":"note","text":"词根记忆：re（再，重新）+leas（松）+e→重新松开→释放"},{"type":"text","text":"discharge, loosen; bounce, dismiss, retire, sack"},{"type":"entry","text":"antebellum","headword":"antebellum"},{"type":"text","text":"adj（尤指）美国内战前的，战前岁月的(belonging to the period before a war,"},{"type":"text","text":"[aenti'belam]"},{"type":"text","text":"especially the American Civil War.)"},{"type":"note","text":"图词根记忆：ante（在前）+bell(战争）+um→战前的"},{"type":"entry","text":"fungible","headword":"fungible"},{"type":"definition","text":"adj. 可取代的(capable of mutual substitution)"},{"type":"text","text":"[qeEpuv,.]"},{"type":"text","text":"interchangeable"},{"type":"entry","text":"untrammeled","headword":"untrammeled"},{"type":"definition","text":"adj. 自由自在的(not confined, limited, or impeded)"},{"type":"text","text":"[An'traemld]"},{"type":"note","text":"词根记忆：un（没有）+trammel（束缚）+ed（的）→没有束缚的→自由自在的"},{"type":"text","text":"unrestrained"},{"type":"entry","text":"demise","headword":"demise"},{"type":"definition","text":"n.终止，死亡(death)"},{"type":"text","text":"[dr'ma1z]"},{"type":"note","text":"图词根记忆：de（离开）+mis（送出）+e→送某人离开这个世界→死亡"}]},{"number":40,"blocks":[{"type":"title","text":"Word List 02 >>>"},{"type":"entry","text":"historiography","headword":"historiography"},{"type":"definition","text":"n.史料编募（the writing of history)"},{"type":"text","text":"[hr,st:ri'a:grafi]"},{"type":"note","text":"图词根记忆：historio（历史）+graphy（写，记录）→写历史→史料编纂"},{"type":"entry","text":"effusive","headword":"effusive"},{"type":"definition","text":"adj. 溢于言表的(showing much or tco much emotion)"},{"type":"text","text":"[r'fju:srv]"},{"type":"note","text":"词根记忆：ef（看作e，出来）+fus（流）+ive→流出的→溢于言表的"},{"type":"text","text":"emotional"},{"type":"text","text":"effusiveness(n.热情洋溢)"},{"type":"entry","text":"hamstring","headword":"hamstring"},{"type":"definition","text":"v. 妨碍，使无能为力(to destroy or hinder the efficiency of; frustrate)"},{"type":"text","text":"['haemstrin]"},{"type":"note","text":"联想记忆：ham（大腿后部）+string（扎）→大腿后部被绳子扎上了，妨碍行动→"},{"type":"text","text":"妨碍"},{"type":"entry","text":"impair","headword":"impair"},{"type":"entry","text":"lethargic","headword":"lethargic"},{"type":"definition","text":"adj. 无精打采的(of, relating to, or characterized by laziness or lack of energy)"},{"type":"text","text":"[la'θa:rdzrk]"},{"type":"text","text":"somnolent, slumberous"},{"type":"entry","text":"mordancy","headword":"mordancy"},{"type":"definition","text":"n.辛辣，尖酸(a biting and caustic quality of style)"},{"type":"text","text":"['mo:rdansi]"},{"type":"note","text":"圆词根记忆：mord（咬）+ancy→咬人的话→辛辣，尖酸"},{"type":"entry","text":"antipredator","headword":"antipredator"},{"type":"definition","text":"adj. 反捕食的(protecting against predation)"},{"type":"text","text":"[enti'predatar]"},{"type":"note","text":"园词根记忆：anti（反对，抗）+predator（捕食性动物）→反捕食的"},{"type":"text","text":"antipredator strategy反捕食策略"},{"type":"entry","text":"counterintuitive","headword":"counterintuitive"},{"type":"definition","text":"adj. 违反常理的(seemingly contrary to common sense)"},{"type":"text","text":"[,kauntarin’tu:rtrv]"},{"type":"text","text":"图组合词：counter（反驳）+intuitive（直觉的）→反驳直觉感受到的→违反常理的"},{"type":"text","text":"unexpected"},{"type":"entry","text":"nepotism","headword":"nepotism"},{"type":"definition","text":"n. 任人唯亲(favoritism shown or patronage granted to relatives, as in business)"},{"type":"text","text":"圈词根记忆：nepo（看作nephew，侄子）+tism→把肥差安排给侄子→任人唯亲"},{"type":"text","text":"[weznedau,]"},{"type":"entry","text":"provisional","headword":"provisional"},{"type":"text","text":"adlj. ll临B时的(provided or serving only for the time being)"},{"type":"text","text":"[pra'v13anl]"},{"type":"text","text":"圆来自provision（n.供给，供养），引申词义“临时的”"},{"type":"text","text":"impermanent, interim, provisionary"},{"type":"text","text":"provisory（aoj有附带条件的）"},{"type":"entry","text":"revel","headword":"revel"},{"type":"definition","text":"v. 王欢f乍乐(to engage in uproarious festivities; make merry)"},{"type":"text","text":"['revl]"},{"type":"entry","text":"predicament","headword":"predicament"},{"type":"definition","text":"n. 图t境(a situation, especially an unpleasant, troublesome one, from which"},{"type":"text","text":"[prr'drkamant]"},{"type":"text","text":"extrication is difficult)"},{"type":"text","text":"dilemma, jam, plight, quandary"},{"type":"entry","text":"sycophantic","headword":"sycophantic"},{"type":"definition","text":"adj.阿奉承的（fawning)"},{"type":"text","text":"[,srka’faentrk]"},{"type":"note","text":"图词根记忆：syco（谄媚）+phant(假装）+ic(-的）→阿奉承的"}]},{"number":41,"blocks":[{"type":"text","text":"<<<GRE词汇精选乱序版"},{"type":"text","text":"While early biographies of Florence Nightingale tended to be quite"},{"type":"text","text":"sycophantic, Lytton Strachey’s irreverent 1918 essay about her ushered in a new"},{"type":"text","text":"era, making it acceptable, even fashionable, to criticize her."},{"type":"text","text":"obsequious, adulating"},{"type":"entry","text":"theatrics","headword":"theatrics"},{"type":"definition","text":"n. 舞台效果(staged or contrived effects);戏剧演出(the art of the theater)"},{"type":"text","text":"[0i'aetrks]"},{"type":"entry","text":"straggler","headword":"straggler"},{"type":"text","text":"ssal buyew jo Amols aou Buow ae oum dnoun e ul ajdoad au) 星Yi u"},{"type":"text","text":"['straeglar]"},{"type":"text","text":"progress than the others)"},{"type":"entry","text":"lavish","headword":"lavish"},{"type":"definition","text":"adj.大量的（expended or produced in abundance);给人印象深刻的：慷概的"},{"type":"text","text":"[laev]"},{"type":"text","text":"(expending or bestowing profusely)"},{"type":"note","text":"园词根记忆：lav(冲洗）+ish→如决堤之水大量涌出→大量的"},{"type":"text","text":"图lavishly（adv.丰富地；浪费地）"}]}]}