{"schemaVersion":1,"bookId":"gre-random","unitId":"word-list-13","title":"Word List 13","sectionId":"gre-core","sectionTitle":"核心词汇","pageStart":158,"pageEnd":170,"extractionMethod":"ocr","wordEntryCount":97,"duplicateEntryCount":62,"pages":[{"number":158,"blocks":[{"type":"title","text":"Word List 13"},{"type":"text","text":"词根/词缀预习表"},{"type":"text","text":"：词根/词级含义"},{"type":"text","text":"例词及释义"},{"type":"text","text":"词根/词缓"},{"type":"text","text":"含义"},{"type":"text","text":"例词及释义"},{"type":"entry","text":"init","headword":"init"},{"type":"text","text":"开始"},{"type":"text","text":"initial adj.开始的，最初的"},{"type":"text","text":"fascin"},{"type":"text","text":"迷住"},{"type":"text","text":"fascinate v迷惑，迷住"},{"type":"text","text":"生命"},{"type":"text","text":"survive v.幸存"},{"type":"entry","text":"stimul","headword":"stimul"},{"type":"text","text":"刺，刺激"},{"type":"text","text":"stimulatev激励：激发"},{"type":"text","text":"viv"},{"type":"text","text":"incorporate v.合并，并人"},{"type":"text","text":"多的"},{"type":"text","text":"multiple adj 多样的，多重的"},{"type":"entry","text":"corpor","headword":"corpor"},{"type":"text","text":"团体"},{"type":"text","text":"multi-"},{"type":"entry","text":"sens","headword":"sens"},{"type":"text","text":"感觉"},{"type":"text","text":"sensory adj. 感觉的，感官的 util"},{"type":"text","text":"用"},{"type":"text","text":"utilize v利用，使用"},{"type":"entry","text":"capt","headword":"capt"},{"type":"text","text":"抓"},{"type":"text","text":"capture v. 俘获 n.战利品"},{"type":"text","text":"cogn"},{"type":"text","text":"知道"},{"type":"text","text":"cognitive aoj认知的"},{"type":"entry","text":"refute","headword":"refute"},{"type":"definition","text":"v. 反驳,驳斥(to prove wrong by argument or evidence; disprove)"},{"type":"text","text":"[rr'fju:t]"},{"type":"note","text":"园词根记忆：re（反）+fut（看作fus，流）+e→反流→反驳，驳斥"},{"type":"entry","text":"assert","headword":"assert"},{"type":"text","text":".断言，主张(to state positively; declare; affirm)"},{"type":"text","text":"[a's3:rt]"},{"type":"note","text":"图词根记忆：as（加强）+sert（加入，插入）→强行插入观点→断言"},{"type":"text","text":"assertory（adj.断言的）;assertion（n.断言，声明；主张）"},{"type":"entry","text":"explicit","headword":"explicit"},{"type":"text","text":"[rk'splrsrt]"},{"type":"text","text":"developed and formulated)"},{"type":"note","text":"园词根记忆：ex（出）+plic（重叠）+it→把重叠在一起的信息弄清楚→清楚的"},{"type":"entry","text":"rival","headword":"rival"},{"type":"definition","text":"n.竞争者，对手（one striving for competitive advantage）v.竞争，与-匹敌（to"},{"type":"text","text":"['rarvl]"},{"type":"text","text":"attempt to equal or surpass)"},{"type":"note","text":"图联想记忆：对手（rival）隔河（river）相望，分外眼红"},{"type":"text","text":"compete, contend, vie"},{"type":"text","text":"unrivaled（adj.无敌的；至高无上的）"}]},{"number":159,"blocks":[{"type":"entry","text":"deferential","headword":"deferential"},{"type":"definition","text":"adj. 顺从的，恭顺的(showing delerence)"},{"type":"text","text":"[,defa'ren]"},{"type":"text","text":"duteous, dutiful"},{"type":"entry","text":"ambiguity","headword":"ambiguity"},{"type":"definition","text":"n.模棱两可的话（an ambiguous word or expression);不明确(uncertainty)"},{"type":"text","text":"[embr'gju:ati]"},{"type":"text","text":"amphibology, equivocality, equivocation, equivoque, tergiversation"},{"type":"text","text":"图 ambiguous (adj. 含期的)"},{"type":"entry","text":"occupation","headword":"occupation"},{"type":"definition","text":"n. 工作， 职业(a job; employment); 占有，占领(the act or process of taking"},{"type":"text","text":"[a:kju'pex{n]"},{"type":"text","text":"possession of a place or area)"},{"type":"text","text":"圆来自occupy（v.占有，占领：忙于）"},{"type":"entry","text":"incorporate","headword":"incorporate"},{"type":"definition","text":"v. 合并, 并入(to combine or join with sth. already formed; embody)"},{"type":"text","text":"[n'ko:rparert]"},{"type":"note","text":"词根记忆：in（进入）+corpor（团体）+ate→（两个公司、机构等）加入团体→合并"},{"type":"text","text":"incorporate..into...使并入；将..包括在内"},{"type":"text","text":"assimilate, imbibe, inhaust, insorb, integrate"},{"type":"entry","text":"intimation","headword":"intimation"},{"type":"definition","text":"n.暗示"},{"type":"text","text":"[intr'merfn]"},{"type":"text","text":"clue, cue, hint, suggestion"},{"type":"entry","text":"obscurity","headword":"obscurity"},{"type":"definition","text":"n. 费解(the quality of being obscure);不出名"},{"type":"text","text":"[ab'skjurati]"},{"type":"text","text":"The civil rights movement did not emerge from obscurity into national"},{"type":"text","text":"prominence overnight; on the contrary, it captured the public's imagination only"},{"type":"text","text":"gradually."},{"type":"entry","text":"entrenched","headword":"entrenched"},{"type":"definition","text":"adj (权利、传统)确立的，牢固的(strongly established and not likely to change)"},{"type":"text","text":"[xn'trentft]"},{"type":"entry","text":"distinguish","headword":"distinguish"},{"type":"definition","text":"v.成为-的特征，使有别于（tomarkasseparate or different)：把-分类（to"},{"type":"text","text":"[dx'strngwj]"},{"type":"text","text":"separate into kinds, classes, or categories);区别,辨别(to discern)"},{"type":"note","text":"词根记忆：di（分开）+sting（刺）+uish→将刺挑出来→区别，辨别"},{"type":"definition","text":"adj感觉的，感官的(of or relating to sensation or to the senses)"},{"type":"entry","text":"instinctive","headword":"instinctive"},{"type":"definition","text":"adj. 本能的(prompted by natural instinct)"}]},{"number":160,"blocks":[{"type":"title","text":"Word List 13 >>>"},{"type":"text","text":"Ethologists are convinced that many animals survive through learning — but"},{"type":"example","text":"learning that is dictated by their genetic programming. learning as thoroughly"},{"type":"text","text":"stereotyped as the most instinctive of behavioral responses."},{"type":"entry","text":"rhetoric","headword":"rhetoric"},{"type":"definition","text":"n.修辞，修辞学：浮夸的言辞（insincere orgrandiloquent language)"},{"type":"text","text":"['retarrk]"},{"type":"text","text":"图来自Rhetor（古希腊的修辞学教师、演说家）"},{"type":"text","text":"日心说"},{"type":"definition","text":"n.公开辩论，论战(dispute，quarrel, strife)"},{"type":"text","text":"地心说"},{"type":"entry","text":"controversy","headword":"controversy"},{"type":"text","text":"['ka:ntrav3:rsi]"},{"type":"note","text":"图词根记忆：contro（相反）+vers（转）+y→意见转向相反的"},{"type":"text","text":"方向→论战"},{"type":"text","text":"altercation, bickering, contention, hurrah"},{"type":"text","text":"controversial(adj引起或可能引起争论的)"},{"type":"entry","text":"predictable","headword":"predictable"},{"type":"definition","text":"adj.可预知的"},{"type":"text","text":"[prr'drktabl]"},{"type":"text","text":"Though dealers insist that professional art dealers can make money in the art"},{"type":"text","text":"market, even an insider's knowledge is not enough: the art world is so fickle that"},{"type":"text","text":"stock-market prices are predictable by comparison."},{"type":"entry","text":"inflexible","headword":"inflexible"},{"type":"definition","text":"adj坚定的，不屈不挑的(rigidly firm in will or purpose)"},{"type":"text","text":"[n'fleksabl]"},{"type":"entry","text":"connotation","headword":"connotation"},{"type":"definition","text":"n. 言外之意， 内涵(idea or notion suggested in addition to its explicit meaning or"},{"type":"text","text":"[ka:na'terfn]"},{"type":"text","text":"denotation)"},{"type":"note","text":"词根记忆：con（共同）+not（注意）+ation→全部注意到的内容→言外之意"},{"type":"entry","text":"stark","headword":"stark"},{"type":"definition","text":"adj.光秃秃的；荒凉的（barren,desolate);（外表)僵硬的（rigid as if in death);完"},{"type":"text","text":"[sta:rk]"},{"type":"text","text":"全的(utter, sheer)"},{"type":"text","text":"Melodramas, which presented stark oppositions between innocence and"},{"type":"text","text":"criminality, virtue and corruption, good and evil, were popular precisely because"},{"type":"text","text":"they offered the audience a world devoid of neutrality"},{"type":"entry","text":"evaluation","headword":"evaluation"},{"type":"definition","text":"n. 评价, 评估(the determined or fixed value of)"}]},{"number":161,"blocks":[{"type":"text","text":"<<<GRE词汇精选乱序版"},{"type":"entry","text":"factual","headword":"factual"},{"type":"definition","text":"adj事实的，实际的（restricted to or based on fact)"},{"type":"text","text":"[faektfual]"},{"type":"text","text":"國来自fact（n.事实）"},{"type":"definition","text":"v.（使）联合，结合(to merge; intermix; blend;possess in combination)：协力(to"},{"type":"entry","text":"combine","headword":"combine"},{"type":"text","text":"[kam'barn]"},{"type":"text","text":"act together)"},{"type":"note","text":"词根记忆：com（共同）+bi（两个）+ne→使两个在一起"},{"type":"text","text":"→（使）联合"},{"type":"text","text":"associate, bracket, coalesce, conjoin"},{"type":"entry","text":"endure","headword":"endure"},{"type":"definition","text":"v. 忍曼，昭承(to suffer sth. painful or uncomfortable"},{"type":"text","text":"[xn'dur]"},{"type":"text","text":"patiently)"},{"type":"note","text":"联想记忆：end（结束）+ure→坚持到结束→忍受，忍耐"},{"type":"text","text":"abide, bear, brook, swallow"},{"type":"text","text":"endure"},{"type":"entry","text":"molecular","headword":"molecular"},{"type":"definition","text":"adji. 分子的(of, relating to, consisting of, or produced by molecules)"},{"type":"text","text":"[ma'lekjalar]"},{"type":"text","text":"园来自molecule（n.分子）"},{"type":"text","text":"macromolecule（n.高分子：大分子）"},{"type":"entry","text":"interpretation","headword":"interpretation"},{"type":"definition","text":"n. 解释，说明(the act or the result of interpreting);演绎(a particular adaptation"},{"type":"text","text":"[1n,t3:rprr'ter{n]"},{"type":"text","text":"or version of a work, method, or style)"},{"type":"text","text":"留 Fossils may be set in stone, but their interpretation is not; a new find may"},{"type":"text","text":"necessitate the revision of a traditional theory."},{"type":"entry","text":"routine","headword":"routine"},{"type":"definition","text":"n.常规(a reiterated speech or formula) adj. 平常的(ordinary)：常规的(of, relating"},{"type":"text","text":"[ru:'tin]"},{"type":"text","text":"to, or being in accordance with established procedure)"},{"type":"note","text":"图联想记忆：例行公事（routine）就是按常规路线（route）走"},{"type":"text","text":"accustomed, customary. quotidian, unremarkable"},{"type":"entry","text":"opponent","headword":"opponent"},{"type":"definition","text":"n.对手，敌手(one that opposes another or others in a battle，contest,"},{"type":"text","text":"[a'paunant]"},{"type":"text","text":"controversy, or debate)"},{"type":"note","text":"词根记忆：op（反）+pon（放）+ent→处于对立位置→对手"},{"type":"text","text":"adversary, antagonist"},{"type":"entry","text":"deviation","headword":"deviation"},{"type":"definition","text":"n. 精高(noticeable or marked departure from accepted norms of behavior)"},{"type":"text","text":"[,di:vi'er{n]"},{"type":"text","text":"aberration, deflection, divergence, diversion"},{"type":"entry","text":"microclimate[n.（尤指有别于周围地区的）小气候]","headword":"microclimate"},{"type":"text","text":"现在是北京时间"},{"type":"text","text":"10点u分2秒"},{"type":"entry","text":"infer","headword":"infer"},{"type":"definition","text":"v.推断，推论，推理(to reach an opinion from reasoning)"},{"type":"text","text":"[xn'f3:r]"},{"type":"note","text":"词根记忆：in（进入）+fer（带来）→带进（意义）→推断"}]},{"number":162,"blocks":[{"type":"title","text":"Word List 13 >>>"},{"type":"entry","text":"prominence","headword":"prominence"},{"type":"definition","text":"n.突出物(something prominent);突出，显著(the quality, state,or fact of being"},{"type":"text","text":"['pra:minans]"},{"type":"text","text":"prominent or conspicuous)"},{"type":"text","text":"Despite the growing prominence of Hispanic actors in the American"},{"type":"text","text":"theater, many Hispanic experts feel that the Spanish speaking population is"},{"type":"text","text":"underrepresented on the stage."},{"type":"text","text":"eminence, kudos, preeminence, prestige"},{"type":"entry","text":"down","headword":"down"},{"type":"definition","text":"n. 绒毛(a covering of soft fluffty feathers): 软毛(fine soft hair)"},{"type":"text","text":"[daun]"},{"type":"entry","text":"detect","headword":"detect"},{"type":"definition","text":"v.洞察(to discover the true character of);查明，探测(to"},{"type":"text","text":"[dr'tekt]"},{"type":"text","text":"discover or determine the existence)"},{"type":"note","text":"园词根记忆：de（去掉）+tect（盖子）→去除盖子→查明"},{"type":"text","text":"detect"},{"type":"text","text":"图detection （n.查明，探测）"},{"type":"entry","text":"ignore","headword":"ignore"},{"type":"definition","text":"v.不顾，不理，忽视（to refuse to take notice of)"},{"type":"text","text":"[rg'no:r]"},{"type":"note","text":"园联想记忆：ig+nore（看作nose，鼻子）→翘起鼻子不理"},{"type":"text","text":"踩→不理"},{"type":"entry","text":"attenuate","headword":"attenuate"},{"type":"definition","text":"v 变薄(to make slender);变弱(to lessen; weaken) adj. 减弱的"},{"type":"text","text":"[a'tenjuert]"},{"type":"note","text":"园词根记忆：at(加强）+tenu（薄）+ate→变薄"},{"type":"text","text":"attenuation（n.变瘦；减少：减弱）"}]},{"number":163,"blocks":[{"type":"entry","text":"advantage","headword":"advantage"},{"type":"definition","text":"n.利益，益处（benefit）v.有利于，有益于"},{"type":"text","text":"[ad'vaentid3]"},{"type":"text","text":"have the advantage of 有-优势"},{"type":"text","text":"allowance, avail, interest"},{"type":"entry","text":"protective","headword":"protective"},{"type":"definition","text":"adj保护的，防护的"},{"type":"text","text":"[pra'tektiv]"},{"type":"text","text":"Why do some plant stems develop a protective bark that enables them to"},{"type":"text","text":"survive the winter, while others shrivel at the first frost?"},{"type":"entry","text":"dissimilar","headword":"dissimilar"},{"type":"definition","text":"adj.不同的，不相似的（unlike)"},{"type":"text","text":"[dt'smrlar]"},{"type":"text","text":"different, disparate, distant, divergent, diverse"},{"type":"entry","text":"tension","headword":"tension"},{"type":"definition","text":"n.紧张，焦虑(anxiety);张力(the amount of a force stretching sth.)"},{"type":"text","text":"['tenfn]"},{"type":"text","text":"国词根记忆：tens（伸展）+ion→伸展出的状态→张力"},{"type":"text","text":"As painted by Constable, the scene is not one of bucolic serenity: rather it"},{"type":"text","text":"shows a striking emotional and intellectual fension,"},{"type":"entry","text":"characteristic","headword":"characteristic"},{"type":"definition","text":"adj有特色的：典型性的n.与众不同的特征"},{"type":"text","text":"[kaerakta'ristik]"},{"type":"text","text":"园来自character（n.性格；特征）"},{"type":"text","text":"uncharacteristic（adj非典型的；非通常的）"},{"type":"entry","text":"multiple","headword":"multiple"},{"type":"definition","text":"adj.多样的，多重的（various; including more than one)"},{"type":"text","text":"['mAltrpl]"},{"type":"note","text":"园词根记忆：multi（多的）+ple（折叠）→多次折叠→多样的，多重的"},{"type":"entry","text":"rush","headword":"rush"},{"type":"definition","text":"v.急促；匆忙行事(to perform in a short time or at a high speed) n. 冲，奔（a"},{"type":"text","text":"[rA]"},{"type":"text","text":"violent forward motion)"},{"type":"text","text":"Having just published his fourth novel in an almost 40-year career, Gaddis"},{"type":"text","text":"describes himself, with some understatement, as a writer who has never been in"}]},{"number":164,"blocks":[{"type":"title","text":"Word List 13 >>>"},{"type":"entry","text":"imminent","headword":"imminent"},{"type":"definition","text":"adj即将发生的，逼近的（about to occur)"},{"type":"text","text":"['rminant]"},{"type":"note","text":"图词根记忆：im（进入）+min（突出）+ent→突进来→逼近的"},{"type":"text","text":"Rosa was such a last-minute worker that she could never start writing a paper"},{"type":"text","text":"till the deadline was imminent,"},{"type":"text","text":"close, impending, proximate"},{"type":"entry","text":"distant","headword":"distant"},{"type":"definition","text":"adj. 疏远的，冷淡的(reserved or aloof in personal relationship)"},{"type":"text","text":"[distant]"},{"type":"note","text":"圆词根记忆：dis（分开）+tant→分开了的→疏远的"},{"type":"text","text":"insociable, unsociable"},{"type":"entry","text":"discernible","headword":"discernible"},{"type":"definition","text":"adj. 可识别的，可辨的(being recognized or identified)"},{"type":"text","text":"[dt'sanabl]"},{"type":"note","text":"词根记忆：dis（分离）+cern（筛选）+ible（可--的）→可识别的"},{"type":"text","text":"Many of the earliest colonial houses that are still standing have been so"},{"type":"text","text":"modified and enlarged that the initial design is no longer dliscernible,"},{"type":"text","text":"indiscernible（adj分辨不清的）"},{"type":"definition","text":"adj偶像破坏的，打破旧习的"},{"type":"entry","text":"iconoclastic","headword":"iconoclastic"},{"type":"text","text":"[ar,ka:na'klaestik]"},{"type":"text","text":"iconoclastic ideas打破旧习的思想"},{"type":"text","text":"iconoclast（n.攻击传统观念或风俗的人）"},{"type":"entry","text":"apply","headword":"apply"},{"type":"definition","text":"v.应用(to put to use);适用(to have relevance or a valid connection)"},{"type":"text","text":"[a'plar]"},{"type":"note","text":"图联想记忆：和supply（v提供）一起记"},{"type":"text","text":"apply to 适用于"},{"type":"text","text":"bestow, employ, exploit, handlle, utilize"},{"type":"entry","text":"perception","headword":"perception"},{"type":"definition","text":"n.感知，知觉（the process，act, or faculty of perceiving)：润察力（quick， acute,"},{"type":"text","text":"[par'sep{n]"},{"type":"text","text":"and intuitive cognition)"},{"type":"text","text":"来自percept（n.感知：感知对象）"},{"type":"entry","text":"intent","headword":"intent"},{"type":"text","text":"adlj.专心的，专注的(having the attention applied; engrossed);热切的，渴望的"},{"type":"text","text":"[rn'tent]"},{"type":"example","text":"(directed with strained or eager attention; full of eager interest) n. 目的, 意向)"},{"type":"text","text":"(purpose)"},{"type":"text","text":"过来自intend（v.打算）"},{"type":"entry","text":"reluctance","headword":"reluctance"},{"type":"definition","text":"n.勉强，不情愿(the quality or state of being reluctant)"},{"type":"text","text":"[rr'laktans]"},{"type":"definition","text":"n. 业余爱好者(one who engages in sth. as a pastime rather than as a profession)"}]},{"number":165,"blocks":[{"type":"entry","text":"irrelevant","headword":"irrelevant"},{"type":"definition","text":"adj.不相关的：不切题的"},{"type":"text","text":"[t'relavant]"},{"type":"text","text":"be irrelevant to与.-不相关"},{"type":"entry","text":"anomaly","headword":"anomaly"},{"type":"definition","text":"n.异常，反常（deviation from common rule）：异常事物（sth.anomalous）"},{"type":"text","text":"[a'na:mali]"},{"type":"note","text":"联想记忆：a+nomal（看作normal,正常的）+y→异常"},{"type":"entry","text":"impartiality","headword":"impartiality"},{"type":"definition","text":"n. 公平, 公正(the quality or state of being just and unbiased)"},{"type":"text","text":"[xm,pa:rfi'aelati]"},{"type":"text","text":"fair"},{"type":"entry","text":"notoriously","headword":"notoriously"},{"type":"definition","text":"adv. 臭名昭著地(in a notorious manner)"},{"type":"text","text":"[nau't:riasli]"},{"type":"text","text":"The testimony of eyewitnesses is notoriously unreliable; emotion and"},{"type":"text","text":"excitement all too often cause our minds to distort what we see."},{"type":"text","text":"notorious（adj.臭名昭著的）"}]},{"number":166,"blocks":[{"type":"title","text":"Word List 13 >>>"},{"type":"entry","text":"extensive","headword":"extensive"},{"type":"definition","text":"adj.广大的，广阔的：多方面的，广泛的（having wide or considerable extent)"},{"type":"text","text":"[rk'stensiv]"},{"type":"text","text":"The development of containers, possibly made from bark or the skins of"},{"type":"text","text":"animals, although this is a matter of conjecture, allowed the extensive sharing of"},{"type":"text","text":"forage foods in prehistoric human societies."},{"type":"entry","text":"reveal","headword":"reveal"},{"type":"definition","text":"v. (神)启示;揭露(to make sth. secret or hidden publicly or"},{"type":"text","text":"[r'vi:1]"},{"type":"text","text":"generally known);显示(to open up to view)"},{"type":"text","text":"Hampshire's assertions, far from showing that we can"},{"type":"text","text":"dismiss the ancient puzzles about objectivity, revea/ the"},{"type":"text","text":"issue to be even more relevant than we had thought."},{"type":"text","text":"disclose, divulge"},{"type":"entry","text":"quantum","headword":"quantum"},{"type":"definition","text":"n. 量子(any of the small subdivisions of a quantized physical magnitude) ;: 定量"},{"type":"text","text":"['kwa:ntam]"},{"type":"note","text":"图词根记忆：quant（数量）+um→定量"},{"type":"entry","text":"attribute","headword":"attribute"},{"type":"text","text":"[a'trbju:t] v. 把-(于(to assign or ascribe to)"},{"type":"text","text":"[aetrrbju:t] n.属性，特质(a characteristic or quality)"},{"type":"note","text":"词根记忆：at（加强）+tribute(给予）→（确定属性前要）给出（原因）→把·归于"},{"type":"text","text":"attribute... t.....·归...."},{"type":"text","text":"trait, virtue"},{"type":"entry","text":"subtly","headword":"subtly"},{"type":"definition","text":"adv.敏锐地，巧妙地"},{"type":"text","text":"['sAtli]"},{"type":"text","text":"artfully, shrewdlly"}]},{"number":167,"blocks":[{"type":"text","text":"<<<GRE词汇精选乱序版"},{"type":"entry","text":"notable","headword":"notable"},{"type":"definition","text":"adj值得注意的，显著的（deserving to be noticed;remarkable)"},{"type":"text","text":"['nautabl]"},{"type":"note","text":"圆词根记忆：not（标示）+able→能被标示的→值得注意的"},{"type":"text","text":"Perhaps predictably, since an ability to communicate effectively is an"},{"type":"text","text":"important trait of any great leader, it has been the exceptional Presidents who"},{"type":"text","text":"have delivered the most notable inaugural addresses."},{"type":"text","text":"distinguished, eminent, famed, memorable, noteworthy"},{"type":"entry","text":"deceptive","headword":"deceptive"},{"type":"definition","text":"adj.欺骗的，导致误解的(tending or having power to"},{"type":"text","text":"deceptive"},{"type":"text","text":"[dr'septiv]"},{"type":"text","text":"deceive)"},{"type":"text","text":"减肥茶"},{"type":"definition","text":"a deceptive advertisement 虚假广告"},{"type":"entry","text":"profitable","headword":"profitable"},{"type":"definition","text":"adj. 有利可图的(affording profits)"},{"type":"text","text":"['pra:fitabl]"},{"type":"text","text":"There are simply no incentives for buying stock in"},{"type":"text","text":"certain industries since rapidly changing environmental"},{"type":"text","text":"restrictions will make a profitable return on any investment"},{"type":"text","text":"very unlikely."},{"type":"text","text":"advantageous, gainful, lucrative, remunerative"},{"type":"entry","text":"steady","headword":"steady"},{"type":"definition","text":"adj.稳定的(direct or sure in movement);不变的(fixed)"},{"type":"text","text":"abiding. constant, equable, stabile, steadfast"},{"type":"text","text":"['stedi]"},{"type":"entry","text":"intensification","headword":"intensification"},{"type":"definition","text":"n.增强，加剧：激烈化"},{"type":"text","text":"[rn,tensifr'ker{n]"},{"type":"text","text":"图来自intensily（v.增强，加剧）"},{"type":"entry","text":"chronological","headword":"chronological"},{"type":"definition","text":"adj按年代顺序排列的(of, relating to, or arranged in or according to the order of"},{"type":"text","text":"[kra:na'la:dzrkl]"},{"type":"text","text":"time)"},{"type":"text","text":"chronicle（n.编年史：历史）"},{"type":"definition","text":"n.精确，准确（precision，exactness）"},{"type":"entry","text":"accuracy","headword":"accuracy"},{"type":"text","text":"['aekjarasi]"},{"type":"note","text":"园词根记忆：ac（加强）+cur（关心）+acy→不断关心才能保证精确→精确"},{"type":"text","text":"accurate（adj 精确的，准确的）"},{"type":"entry","text":"ultimately","headword":"ultimately"},{"type":"definition","text":"adv.最后，终于(in the end,eventually)"},{"type":"text","text":"['sltrmatli]"},{"type":"text","text":"Just as all roads once led to Rome, all blood vessels in the human body"},{"type":"text","text":"ultimately empty into the heart."},{"type":"entry","text":"intractable","headword":"intractable"},{"type":"definition","text":"adj倔强的，难以管理的(not easily managed;unruly or stubborn);难以加工"},{"type":"text","text":"[xn'traektabl]"},{"type":"text","text":"的，难以操作的(difficult to mold or manipulate)"}]},{"number":168,"blocks":[{"type":"title","text":"Word List 13 >>>"},{"type":"note","text":"图词根记忆：in（不）+tract（拉）+able→拉不动的→促强的"},{"type":"text","text":"intractability（n.难处理性，难驾驭）"},{"type":"entry","text":"academic","headword":"academic"},{"type":"definition","text":"adj. 学院的，学术的(associated with an academy or school)：理论的(theoretical)"},{"type":"text","text":"[aeka'demrk]"},{"type":"text","text":"园来自academy（n.学院，学术团体）"},{"type":"text","text":"图academic field 学术领域"},{"type":"entry","text":"temporary","headword":"temporary"},{"type":"definition","text":"adj. 暂时的,临时的(lasting for a limited time)"},{"type":"text","text":"['tempareri]"},{"type":"note","text":"图词根记忆：tempor（时间）+ary→时间很短→暂时的"},{"type":"text","text":"Only by ignoring decades of mismanagement and inefficiency could investors"},{"type":"text","text":"conclude that a fresh infusion of cash would provide anything more than a"},{"type":"text","text":"termporary solution to the company's financial woes."},{"type":"entry","text":"subjective","headword":"subjective"},{"type":"definition","text":"adj. 主观的,想象的(influenced by personal feelings and therefore perhaps"},{"type":"text","text":"[sab'dzektrv]"},{"type":"text","text":"unfair)"},{"type":"text","text":"图来自subject（n.主题）"},{"type":"entry","text":"worthy","headword":"worthy"},{"type":"definition","text":"adj. 值得的(having worth or value)：有价值的(having sufficient worth or"},{"type":"text","text":"['w3:rdi]"},{"type":"text","text":"importance) n. 知名 人±(a worthy or prominent person)"},{"type":"entry","text":"presume","headword":"presume"},{"type":"definition","text":"v. 推测，假定(to take for granted as being true in the absence of proof to the"},{"type":"text","text":"[prr'zu:m]"},{"type":"text","text":"contrary): 认定E(to give reasonable evidence for assuming)"},{"type":"note","text":"圆词根记忆：pre（预先）+sum（抓住）+e→预先抓住→推测，假定"},{"type":"entry","text":"obvious","headword":"obvious"},{"type":"definition","text":"adj明显的，显而易见的(easy to see and understand)"},{"type":"text","text":"[a:bvias]"},{"type":"note","text":"词根记忆：ob（加强）+vi（路）+ous→在路上的，随处可见→明显的"},{"type":"text","text":"While not teeming with the colorfully obvious forms of life that are found in a"},{"type":"example","text":"tropical rain forest, the desert is host to a surprisingly large number of species."},{"type":"text","text":"apparent, evident, manifest, palpable"},{"type":"entry","text":"compliance","headword":"compliance"},{"type":"definition","text":"n. 顺从, 遵从(obedience to a rule, agreement or demand)"},{"type":"text","text":"[kam'plarans]"},{"type":"text","text":"圆来自comply（v.顺从）"},{"type":"entry","text":"ecological","headword":"ecological"},{"type":"definition","text":"adj生态的：生态学的"},{"type":"text","text":"[i:ka'la:d3rkl]"},{"type":"text","text":"With the evolution of wings, insects were able to disperse to the far ecological"},{"type":"text","text":"comers, across deserts and bodies of water, to reach new food sources and"},{"type":"text","text":"inhabit a wider variety of promising environmental niches."},{"type":"entry","text":"variety","headword":"variety"},{"type":"definition","text":"n.多样性(the quality or state of having different forms or types)：种类"},{"type":"text","text":"[va'rarati]"},{"type":"text","text":"(assortment)：变种(subspecies)"},{"type":"text","text":"国词根记忆：vari(改变）+ety→多样性"},{"type":"text","text":"The theory of cosmic evolution states that the universe, having begun in a"},{"type":"text","text":"state of simplicity and homogeneity, has differentiated into great variety."}]},{"number":169,"blocks":[{"type":"text","text":"<<<GRE词汇精选乱序版"},{"type":"text","text":"visible"},{"type":"entry","text":"visible","headword":"visible"},{"type":"definition","text":"ad可见的，看得见的（capable of being seen）;能注意到"},{"type":"text","text":"['vizabl]"},{"type":"text","text":"的(exposed to view);明显的，可察觉到的(capable of"},{"type":"text","text":"perceived)"},{"type":"text","text":"国词根记忆：vis（看）+ible（可的）→看得见的：明显的"},{"type":"entry","text":"persist","headword":"persist"},{"type":"definition","text":"v.坚持不懈，执意（to go on resolutely in spite of opposition)：坚持问，不停地说"},{"type":"text","text":"[par'sist]"},{"type":"text","text":"(to be insistent in the repetition or pressing of an utterance);继续存在，长存(to"},{"type":"text","text":"continue in existence; last)"},{"type":"note","text":"园词根记忆：per（始终）+sist（坐）→始终坐着→坚持不懈"},{"type":"text","text":"The chances that a species will persist are reduced if any vital function is"},{"type":"text","text":"restricted to a single kind of organ; redundancy by itself possesses an enormous"},{"type":"text","text":"survival advantage."},{"type":"text","text":"abide, endure, perdure, persevere"},{"type":"entry","text":"clarify","headword":"clarify"},{"type":"definition","text":"v. 澄清(to cause sth. to become clear to understand)"},{"type":"text","text":"['klaerafar]"},{"type":"note","text":"园词根记忆：clar（清楚，明白）+ify（化）→澄清"},{"type":"text","text":"elucidate, illuminate, illustrate"},{"type":"text","text":"clarification（n.解释，澄清）"},{"type":"entry","text":"sustain","headword":"sustain"},{"type":"definition","text":"v.承受（困难)（undergo)：支撑（重量或压力)(to carry or withstand a weight or"},{"type":"text","text":"[sa'stein]"},{"type":"text","text":"pressure)"},{"type":"note","text":"圆词根记忆：Sus（下）+tain（拿住）→在下面支撑住→支撑"},{"type":"text","text":"bolster, prop, underprop"},{"type":"entry","text":"adaptive","headword":"adaptive"},{"type":"definition","text":"adj. 适应的(showing or having a capacity for or tendency toward adaptation)"},{"type":"text","text":"[a'daptrv]"},{"type":"text","text":"adaptability (n.适应性)"},{"type":"entry","text":"strategic","headword":"strategic"},{"type":"definition","text":"adj.战略上的(of, relating to,or marked by strategy);关键的，重要的(necessary"},{"type":"text","text":"[stra'ti:d31k]"},{"type":"text","text":"to or important in the initiation, conduct, or completion of a strategic plan)"},{"type":"entry","text":"rigidity","headword":"rigidity"},{"type":"definition","text":"n.严格；坚硬，僵硬(the quality or state of being rigid)"},{"type":"text","text":"[rr'dzidati]"},{"type":"text","text":"The child needed physical therapy to counteract the rigidliry that had tragically"},{"type":"text","text":"immobilized his legs."},{"type":"entry","text":"modify","headword":"modify"},{"type":"definition","text":"v. 修改,更改(to alter partially; amend)"},{"type":"text","text":"['ma:drfar]"},{"type":"note","text":"图词根记忆：mod（方式）+ity→使改变方式→修改，更改"},{"type":"entry","text":"publicize","headword":"publicize"},{"type":"text","text":"（公开）宣传，宣扬：引人注意"},{"type":"text","text":"['pAblrsarz]"},{"type":"note","text":"图词根记忆：public（公开的）+ize（使）→使公开→宣传，宣扬"},{"type":"text","text":"Though the ad writers had come up with a highly creative campaign to"},{"type":"text","text":"publicize the company's newest product, the head office rejected it for a more"},{"type":"text","text":"prosaic, down-to-earth approach."}]},{"number":170,"blocks":[{"type":"title","text":"Word List 13 >>>"},{"type":"entry","text":"structure","headword":"structure"},{"type":"definition","text":"n.结构(makeup) v 建造(to construct)"},{"type":"text","text":"['strAktfar]"},{"type":"text","text":"Even though the basic organization of the brain does not change after birth,"},{"type":"text","text":"details of its structure and function remain plastic for some time, particularly in"},{"type":"text","text":"the cerebral cortex."},{"type":"entry","text":"nomadic","headword":"nomadic"},{"type":"definition","text":"adj.游牧的（of nomad)：流浪的"},{"type":"text","text":"[nau'maedik]"},{"type":"text","text":"itinerant, peripatetic, vagabond, vagrant"},{"type":"entry","text":"problematic","headword":"problematic"},{"type":"definition","text":"adj.成问题的（posing a problem)：有疑问的，值得怀疑的（open to doubt;"},{"type":"text","text":"[pra:bla'maetrk]"},{"type":"text","text":"debatable);未知的，未解决的(not definite or seled)"},{"type":"text","text":"As early as the seventeenth century, philosophers called attention to the"},{"type":"text","text":"problematic character of the issue, and their twentieth-century counterparts still"},{"type":"text","text":"approach it with uneasiness."},{"type":"entry","text":"incongruous","headword":"incongruous"},{"type":"definition","text":"adj.不协调的，不—致的(incompatible;disagreeing: inconsistent within itself;"},{"type":"text","text":"[xn'ka:ngruas]"},{"type":"text","text":"unsuitable)"},{"type":"entry","text":"alternative","headword":"alternative"},{"type":"text","text":"alternative"},{"type":"definition","text":"adj轮流的，交替的（alternate)：两者择一的（offering or"},{"type":"text","text":"AB"},{"type":"text","text":"[:l’t3:rnatrv]"},{"type":"text","text":"expressing a choice)"},{"type":"note","text":"词根记忆：altern（改变状态，其他的）+ative（的）→改"},{"type":"text","text":"变状态的→轮流的，交替的"},{"type":"text","text":"backup, substitute, surrogate"},{"type":"entry","text":"adequate","headword":"adequate"},{"type":"definition","text":"adj. 足够的(sufficient)"},{"type":"text","text":"[edikwat]"},{"type":"note","text":"园词根记忆：ad（加强）+equ（平等）+ate(的）→比平等多的→足够的"},{"type":"text","text":"competent, satisfactory"}]}]}