{"schemaVersion":1,"bookId":"situational-15000","unitId":"scene-279","title":"棋牌游戏","sectionId":"chapter-12","sectionTitle":"休闲娱乐无极限","pageStart":1360,"pageEnd":1364,"extractionMethod":"text-layer","wordEntryCount":33,"duplicateEntryCount":13,"pages":[{"number":1360,"blocks":[{"type":"title","text":"279 棋牌游戏"},{"type":"section","text":"Step1 场景词"},{"type":"entry","text":"chess [tʃes]","headword":"chess"},{"type":"definition","text":"n.国际象棋"},{"type":"note","text":"◎play chess下国际象棋/chess player国际象棋手"},{"type":"entry","text":"chessman [ˈtʃesmæn]","headword":"chessman"},{"type":"definition","text":"n.国际象棋的棋子"},{"type":"entry","text":"chessboard [ˈtʃesbɔːd]","headword":"chessboard"},{"type":"definition","text":"n.国际象棋棋盘"},{"type":"entry","text":"chinese chess 中国象棋","headword":"chinese chess"},{"type":"entry","text":"go [ɡəʊ]","headword":"go"},{"type":"definition","text":"n.围棋"},{"type":"entry","text":"reversi [rɪˈvɜːsi]","headword":"reversi"},{"type":"definition","text":"n.黑白棋"},{"type":"entry","text":"military chess 军棋","headword":"military chess"},{"type":"entry","text":"draughts [drɑːfts]","headword":"draughts"},{"type":"definition","text":"n.跳棋"},{"type":"entry","text":"checkers [ˈtʃekəz]","headword":"checkers"},{"type":"definition","text":"n.西洋棋"}]},{"number":1361,"blocks":[{"type":"entry","text":"five-in-a-row [ˌfaɪv ɪn ə ˈrəʊ]","headword":"five-in-a-row"},{"type":"definition","text":"n.五子棋"},{"type":"entry","text":"mahjong [mɑːˈdʒɒŋ]","headword":"mahjong"},{"type":"definition","text":"n.麻将"},{"type":"entry","text":"poker [ˈpəʊkə(r)]","headword":"poker"},{"type":"definition","text":"n.扑克"},{"type":"entry","text":"king [kɪŋ]","headword":"king"},{"type":"definition","text":"n.（国际象棋的）王；（扑克牌的）老K"},{"type":"entry","text":"rook [rʊk]","headword":"rook"},{"type":"definition","text":"n.（国际象棋的）车"},{"type":"entry","text":"knight [naɪt]","headword":"knight"},{"type":"definition","text":"n.（国际象棋中的）马"}]},{"number":1362,"blocks":[{"type":"entry","text":"castling [ˈkɑːslɪŋ]","headword":"castling"},{"type":"definition","text":"n.王车易位"},{"type":"entry","text":"en passant 吃过路兵","headword":"en passant"},{"type":"entry","text":"bingo [ˈbɪŋɡəʊ]","headword":"bingo"},{"type":"definition","text":"n.宾戈游戏（一种赌博或有奖的游戏）"},{"type":"entry","text":"domino [ˈdɒmɪnəʊ]","headword":"domino"},{"type":"definition","text":"n.多米诺骨牌"},{"type":"entry","text":"baccarat [ˈbækərɑː]","headword":"baccarat"},{"type":"definition","text":"n.巴卡拉纸牌游戏，百家乐（一种纸牌赌博游戏）"},{"type":"entry","text":"texas poker 德克萨斯扑克","headword":"texas poker"},{"type":"entry","text":"five card stud 五张桩牌扑克，梭哈","headword":"five card stud"},{"type":"entry","text":"blackjack [ˈblækdʒæk]","headword":"blackjack"},{"type":"definition","text":"n.二十一点纸牌游戏"},{"type":"entry","text":"hit [hɪt]","headword":"hit"},{"type":"definition","text":"v.叫牌"},{"type":"entry","text":"stand [stænd]","headword":"stand"}]},{"number":1363,"blocks":[{"type":"definition","text":"v.停叫"},{"type":"entry","text":"play cards 打牌","headword":"play cards"},{"type":"entry","text":"bet [bet]","headword":"bet"},{"type":"definition","text":"n.赌注"},{"type":"definition","text":"v.下注"},{"type":"note","text":"◎bet on就…打赌"},{"type":"entry","text":"wager [ˈweɪdʒə(r)]","headword":"wager"},{"type":"definition","text":"n.赌注"},{"type":"entry","text":"ante [ˈænti]","headword":"ante"},{"type":"definition","text":"v.下赌注"},{"type":"entry","text":"buy in 买进","headword":"buy in"},{"type":"entry","text":"call [kɔːl]","headword":"call"},{"type":"definition","text":"v.跟注"},{"type":"entry","text":"all in 全部跟进","headword":"all in"}]},{"number":1364,"blocks":[{"type":"entry","text":"card shark （口）玩纸牌老手","headword":"card shark"},{"type":"section","text":"Step2 学以致用"},{"type":"section","text":"Conversation 1"},{"type":"example","text":"A：I find a set of chessmen; let's play chess.（我找到一副国际象"},{"type":"text","text":"棋，咱们下棋吧。）"},{"type":"example","text":"B：But we don't have a chessboard.（可是咱们没有棋盘啊。）"},{"type":"section","text":"Conversation 2"},{"type":"example","text":"A：What's the minimum bet?（最少要下注多少？）"},{"type":"example","text":"B：Minimum wager is 5 dollars.（最少5美元。）"}]}]}