{"schemaVersion":1,"bookId":"situational-15000","unitId":"scene-011","title":"谈论装修事宜","sectionId":"chapter-01","sectionTitle":"居家琐事会表达","pageStart":75,"pageEnd":80,"extractionMethod":"text-layer","wordEntryCount":25,"duplicateEntryCount":27,"pages":[{"number":75,"blocks":[{"type":"title","text":"11 谈论装修事宜"},{"type":"section","text":"Step1 场景词"},{"type":"entry","text":"moulding [ˈməʊldɪŋ]","headword":"moulding"},{"type":"definition","text":"n.装饰嵌线；铸造"},{"type":"entry","text":"equip with 配备…","headword":"equip with"}]},{"number":76,"blocks":[{"type":"entry","text":"plane graph 平面图","headword":"plane graph"},{"type":"entry","text":"feng shui 风水","headword":"feng shui"},{"type":"entry","text":"subtle design 精妙的设计","headword":"subtle design"},{"type":"entry","text":"tremendous task 艰巨的任务","headword":"tremendous task"},{"type":"entry","text":"joiner [ˈdʒɔɪnə(r)]","headword":"joiner"},{"type":"definition","text":"n.木工"},{"type":"entry","text":"wireman [ˈwaɪəmən]","headword":"wireman"},{"type":"definition","text":"n.电工"},{"type":"entry","text":"sand [sænd]","headword":"sand"},{"type":"definition","text":"n.沙"},{"type":"note","text":"◎sand storm沙尘暴"}]},{"number":77,"blocks":[{"type":"entry","text":"plaster board 石膏板","headword":"plaster board"},{"type":"entry","text":"composite board 复合板","headword":"composite board"},{"type":"entry","text":"shavings [ʃeɪvɪŋz]","headword":"shavings"},{"type":"definition","text":"n.刨花"}]},{"number":78,"blocks":[{"type":"entry","text":"paint roller 油漆滚子，滚漆筒","headword":"paint roller"},{"type":"entry","text":"putty [ˈpʌti]","headword":"putty"},{"type":"definition","text":"n.腻子"},{"type":"note","text":"◎putty knife腻子刀"},{"type":"entry","text":"emulsion paint 乳胶漆","headword":"emulsion paint"},{"type":"entry","text":"glass cement 玻璃胶","headword":"glass cement"},{"type":"entry","text":"strong current 强电","headword":"strong current"},{"type":"entry","text":"weak current 弱电","headword":"weak current"},{"type":"entry","text":"pendent lamp 吊灯","headword":"pendent lamp"},{"type":"entry","text":"weather bar 防水条","headword":"weather bar"},{"type":"entry","text":"triangular valve 三角阀","headword":"triangular valve"}]},{"number":79,"blocks":[{"type":"entry","text":"background wall 背景墙","headword":"background wall"},{"type":"entry","text":"bay window 飘窗","headword":"bay window"},{"type":"entry","text":"central heating 集中供暖","headword":"central heating"},{"type":"entry","text":"regular maintenance 定期维护","headword":"regular maintenance"},{"type":"section","text":"Step2 学以致用"},{"type":"section","text":"Conversation 1"},{"type":"example","text":"A：Steven said that the wallpaper and the moulding of the wall are"},{"type":"text","text":"excellent. （史蒂文说壁纸和墙面的装饰嵌线都非常不错。）"},{"type":"example","text":"B：I agree with him.（我同意他的说法。）"}]},{"number":80,"blocks":[{"type":"section","text":"Conversation 2"},{"type":"example","text":"A：So are you going to hire someone to paint your house? （那么你"},{"type":"text","text":"打算雇人给你粉刷房子吗？）"},{"type":"example","text":"B：No. I plan to repaint our house by myself.（不，我打算自己把房"},{"type":"text","text":"子重新粉刷一遍。）"}]}]}