{"schemaVersion":1,"bookId":"toefl-sentences","unitId":"sentence-035","title":"Sentence 35","sectionId":"sentences-031","sectionTitle":"Sentence 31-40","pageStart":238,"pageEnd":243,"extractionMethod":"text-layer","wordEntryCount":30,"duplicateEntryCount":7,"pages":[{"number":238,"blocks":[{"type":"title","text":"Sentence 35"},{"type":"text","text":"Research into the dynamics of storms is directed toward improving"},{"type":"text","text":"the ability to predict these events and thus to minimize damage and avoid"},{"type":"text","text":"loss of life."},{"type":"text","text":"对风暴动力学的研究旨在提高对这类风暴事件预测的能力，从"},{"type":"text","text":"而减少损失，避免人员伤亡。"},{"type":"section","text":"语法笔记"},{"type":"text","text":"本句的主干是Research is directed toward improving the ability。"},{"type":"text","text":"ability之后的不定式“to predict ... and thus to minimize ... and avoid ...”作"},{"type":"text","text":"ability的后置定语。"},{"type":"section","text":"核心词表"}]},{"number":239,"blocks":[{"type":"entry","text":"minimize /ˈmɪnɪmaɪz/ vt. 将…减到最少；最小化","headword":"minimize"},{"type":"note","text":"记忆 minim（小量）+ize（…化）→最小化"},{"type":"note","text":"反义 maximize vt. 最大化"},{"type":"note","text":"同根 minimum a. 最低的"},{"type":"entry","text":"damage /ˈdæmɪdʒ/ n./v. 毁坏，损害","headword":"damage"},{"type":"note","text":"同义 destroy v. 破坏"},{"type":"entry","text":"avoid /əˈvɔɪd/ vt. 避免，规避","headword":"avoid"},{"type":"note","text":"记忆 a（加强）+void（空旷；空虚）→空出来→回避"},{"type":"note","text":"同根 avoidable a. 可避免的"},{"type":"text","text":"avoidance n. 避免"},{"type":"section","text":"主题归纳"}]},{"number":240,"blocks":[{"type":"text","text":"与“气候”相关的词："}]},{"number":241,"blocks":[{"type":"entry","text":"barometric /ˌbærəˈmetrɪk/ a. 气压的","headword":"barometric"},{"type":"note","text":"同根 barometer n. 气压计"},{"type":"text","text":"cold front 冷锋"},{"type":"text","text":"cold low 冷低压"},{"type":"text","text":"cold wave 寒流"},{"type":"entry","text":"evaporate /ɪˈvæpəreɪt/ v. （使）蒸发；消失","headword":"evaporate"},{"type":"note","text":"同根 evaporation n. 蒸发"},{"type":"entry","text":"humid /ˈhjuːmɪd/ a. 潮湿的，湿润的","headword":"humid"},{"type":"note","text":"同根 humidity n. 湿度"},{"type":"entry","text":"meteorology /ˌmiːtiəˈrɑːlədʒi/ n. 气象学","headword":"meteorology"},{"type":"note","text":"同根 meteorologist n. 气象学者"},{"type":"text","text":"thermal high 热高压"},{"type":"entry","text":"tide /taɪd/ n. 潮汐；潮流","headword":"tide"},{"type":"note","text":"同根 tidal a. 潮汐的"},{"type":"entry","text":"tropic /ˈtrɑːpɪk/ n. 回归线；热带 a. 热带的","headword":"tropic"},{"type":"note","text":"同根 tropical a. 热带的"},{"type":"entry","text":"twilight /ˈtwaɪlaɪt/ n. 暮色，微光","headword":"twilight"}]},{"number":242,"blocks":[{"type":"note","text":"搭配 in the twilight 黄昏时分"},{"type":"text","text":"“自然灾害”及相关词："},{"type":"entry","text":"aftershock /ˈæftərʃɑːk/ n. 余震","headword":"aftershock"},{"type":"note","text":"搭配 aftershock wave 余震波"},{"type":"entry","text":"avalanche /ˈævəlæntʃ/ n./vi. 雪崩","headword":"avalanche"},{"type":"note","text":"同义 snowslide n. 雪崩"},{"type":"entry","text":"blizzard /ˈblɪzərd/ n. 暴风雪","headword":"blizzard"},{"type":"note","text":"搭配 blizzard fatality 雪暴灾害"},{"type":"entry","text":"crest /krest/ n. 洪峰","headword":"crest"},{"type":"entry","text":"cyclone /ˈsaɪkloʊn/ n. 旋风；气旋","headword":"cyclone"},{"type":"entry","text":"drought /draʊt/ n. 干旱，旱灾","headword":"drought"},{"type":"note","text":"搭配 drought disaster 旱灾"},{"type":"entry","text":"earthquake /ˈɜːrθkweɪk/ n. 地震","headword":"earthquake"},{"type":"note","text":"搭配 predict an earthquake 预测地震"},{"type":"entry","text":"frost /frɑːst/ n. 霜冻；严寒 v. 结霜","headword":"frost"},{"type":"note","text":"搭配 ground frost 地面霜"},{"type":"entry","text":"hurricane /ˈhɜːrəkən/ n. 飓风","headword":"hurricane"},{"type":"entry","text":"landslide /ˈlændslaɪd/ n. 山崩","headword":"landslide"},{"type":"note","text":"记忆 land（地）+slide（滑行）→地向下滑→山崩"},{"type":"entry","text":"tornado /tɔːrˈneɪdoʊ/ n. 龙卷风","headword":"tornado"},{"type":"note","text":"记忆 tornad（=turn转）+o（表物）→转的风→龙卷风"},{"type":"entry","text":"typhoon /taɪˈfuːn/ n. 台风","headword":"typhoon"},{"type":"note","text":"搭配 typhoon eye 台风眼"},{"type":"entry","text":"calamity /kəˈlæməti/ n. 大灾祸，不幸事件","headword":"calamity"},{"type":"note","text":"同根 calamitous a. 灾难性的"}]},{"number":243,"blocks":[{"type":"entry","text":"famine /ˈfæmɪn/ n. 饥荒","headword":"famine"},{"type":"note","text":"搭配 severe famine 严重饥荒"},{"type":"entry","text":"lava /ˈlɑːvə/ n. 熔岩","headword":"lava"},{"type":"note","text":"同义 magma n. 岩浆"},{"type":"entry","text":"devastate /ˈdevəsteɪt/ vt. 蹂躏，破坏","headword":"devastate"},{"type":"note","text":"记忆 de（表加强）+vast（空）+ate（使…）→使变空→破坏"},{"type":"entry","text":"evacuation /ɪˌvækjuˈeɪʃn/ n. 撤离","headword":"evacuation"},{"type":"note","text":"同根 evacuate v. 撤离"},{"type":"entry","text":"rescue /ˈreskjuː/ n./vt. 救援","headword":"rescue"},{"type":"note","text":"搭配 rescue crew 救援人员"},{"type":"entry","text":"survivor /sərˈvaɪvər/ n. 幸存者","headword":"survivor"},{"type":"note","text":"同根 survival n. 生存，幸免"},{"type":"entry","text":"wreckage /ˈrekɪdʒ/ n. 残骸","headword":"wreckage"},{"type":"note","text":"搭配 aircraft wreckage 飞机残骸"}]}]}