{"schemaVersion":1,"bookId":"toefl-sentences","unitId":"sentence-099","title":"Sentence 99","sectionId":"sentences-091","sectionTitle":"Sentence 91-100","pageStart":647,"pageEnd":652,"extractionMethod":"text-layer","wordEntryCount":30,"duplicateEntryCount":12,"pages":[{"number":647,"blocks":[{"type":"title","text":"Sentence 99"},{"type":"text","text":"Though it may be difficult to imagine from a later perspective, a"},{"type":"text","text":"strain of critical opinion in the 1920s predicted that sound film would be a"},{"type":"text","text":"technical novelty that would soon fade from sight, just as had many"},{"type":"text","text":"previous attempts, dating well back before the First World War, to link"},{"type":"text","text":"images with recorded sound."},{"type":"text","text":"虽然从后来的视角来看也许难以想象，但是在20世纪20年代，"},{"type":"text","text":"一种批判性观点预测有声电影这项技术新玩意儿将会迅速淡出人们"},{"type":"text","text":"的视线，就像之前——追溯到第一次世界大战之前——多次试图将"},{"type":"text","text":"画面与录音连在一起的技术那样。"},{"type":"section","text":"语法笔记"},{"type":"text","text":"本句的主干是“A strain of opinion predicted that ...”。That引导一个"},{"type":"text","text":"宾语从句，该宾语从句中包含一个that引导的定语从句that would soon"},{"type":"text","text":"fade from sight，修饰a technical novelty。其后又有一个as引导的状语从"},{"type":"text","text":"句“as had many ... recorded sound”，as表示“正如、像、和…一样”。现"},{"type":"text","text":"在分词短语dating well back before the First World War作后置定语修饰"},{"type":"text","text":"many previous attempts。"},{"type":"section","text":"核心词表"}]},{"number":648,"blocks":[{"type":"entry","text":"critical /ˈkrɪtɪkl/ a. 批评的；危急的；关键的","headword":"critical"},{"type":"note","text":"搭配 critical thinking 批判性思维"},{"type":"note","text":"同根 critically ad. 批评地"},{"type":"entry","text":"technical /ˈteknɪkl/ a. 技术的，工艺的","headword":"technical"},{"type":"note","text":"记忆 techn（技术）+ical（…的）→技术的"},{"type":"note","text":"搭配 technical innovation 技术革新"},{"type":"note","text":"同根 technically ad. 技术上"},{"type":"entry","text":"novelty /ˈnɑːvlti/ n. 新奇，新颖，新奇的事物","headword":"novelty"},{"type":"note","text":"记忆 novel（新的）+ty（性质、状态）→新奇，新颖"},{"type":"note","text":"同义 newness n. 新奇"},{"type":"entry","text":"fade /feɪd/ v. 消失；褪色；凋谢","headword":"fade"},{"type":"note","text":"搭配 fade away 渐渐消失"},{"type":"note","text":"同义 vanish vi. 消失"},{"type":"section","text":"主题归纳"}]},{"number":649,"blocks":[{"type":"text","text":"与“电影制作”相关的词："},{"type":"entry","text":"adaptation /ˌædæpˈteɪʃn/ n. 改编","headword":"adaptation"},{"type":"note","text":"同根 adapt vt. 改编；改写"},{"type":"entry","text":"cast /kæst/ vt. 投射（光、视线等）","headword":"cast"},{"type":"definition","text":"n. 全体演员"},{"type":"note","text":"搭配 a cast list 演员表"},{"type":"entry","text":"casting /ˈkæstɪŋ/ n. 选角","headword":"casting"},{"type":"entry","text":"cutting /ˈkʌtɪŋ/ n. 剪辑","headword":"cutting"},{"type":"entry","text":"dolly /ˈdɑːli/ n. 移动式摄影小车","headword":"dolly"},{"type":"note","text":"搭配 dolly camera 伸缩镜头"},{"type":"entry","text":"dub /dʌb/ v. 为（电影等）配音","headword":"dub"}]},{"number":650,"blocks":[{"type":"entry","text":"edit /ˈedɪt/ vt. 编辑","headword":"edit"},{"type":"note","text":"同根 editor n. 编辑"},{"type":"entry","text":"exterior /ɪkˈstɪriər/ n. 外景；外部","headword":"exterior"},{"type":"note","text":"反义 interior n. 内景"},{"type":"text","text":"film crew 影片摄制组"},{"type":"text","text":"full shot 全景"},{"type":"text","text":"long shot 远景"},{"type":"entry","text":"montage /ˌmɑːnˈtɑːʒ/ n. 蒙太奇；画面剪辑","headword":"montage"},{"type":"note","text":"搭配 montage director 剪辑指导"},{"type":"entry","text":"poster /ˈpoʊstər/ n. 海报，宣传画","headword":"poster"},{"type":"note","text":"同根 post v. 张贴"},{"type":"entry","text":"preview /ˈpriːvjuː/ n./v. 预映，预演","headword":"preview"},{"type":"note","text":"记忆 pre（预先）+view（看）→预映，预演"},{"type":"entry","text":"prop /prɑːp/ n. 小道具","headword":"prop"},{"type":"note","text":"搭配 clothing prop 服饰道具"},{"type":"entry","text":"recast /ˌriːˈkæst/ v. 重新安排角色","headword":"recast"},{"type":"note","text":"记忆 re（重新）+cast（演员）→重新安排角色"},{"type":"text","text":"release time 上映时间"},{"type":"entry","text":"scenarist /sɪˈnɑːrɪst/ n. 电影剧本作者，编剧家","headword":"scenarist"},{"type":"note","text":"搭配 scenarist director 编导"},{"type":"entry","text":"screening /ˈskriːnɪŋ/ n. 放映","headword":"screening"},{"type":"entry","text":"screenplay /ˈskriːnpleɪ/ n. 电影剧本","headword":"screenplay"},{"type":"note","text":"搭配 screenplay adaptation 剧本改编"},{"type":"entry","text":"scriptwriting /ˈskrɪptraɪtɪŋ/ n. 编剧","headword":"scriptwriting"},{"type":"note","text":"参考 script n. 剧本"}]},{"number":651,"blocks":[{"type":"entry","text":"shooting /ˈʃuːtɪŋ/ n. 拍摄","headword":"shooting"},{"type":"note","text":"搭配 shooting schedule 拍摄日程"},{"type":"text","text":"shooting angle 拍摄角度"},{"type":"text","text":"special effect 特技"},{"type":"entry","text":"spotlight /ˈspɑːtlaɪt/ n. 聚光灯","headword":"spotlight"},{"type":"note","text":"搭配 in the spotlight 在聚光灯下"},{"type":"text","text":"visual effect 视觉效果"},{"type":"text","text":"与“科技创新”相关的词："},{"type":"entry","text":"achievement /əˈtʃiːvmənt/ n. 成果","headword":"achievement"},{"type":"note","text":"同根 achieve vt. 取得"},{"type":"entry","text":"industrialize /ɪnˈdʌstriəlaɪz/ v. 使工业化；实现工业化","headword":"industrialize"},{"type":"note","text":"同根 industry n. 工业"},{"type":"entry","text":"initiative /ɪˈnɪʃətɪv/ n. 主动性；主创精神","headword":"initiative"},{"type":"definition","text":"a. 主动的"},{"type":"note","text":"搭配 take the initiative 采取主动；带头"}]},{"number":652,"blocks":[{"type":"entry","text":"intellectual /ˌɪntəˈlektʃuəl/ a. 智力的","headword":"intellectual"},{"type":"note","text":"同根 intellect n. 智力"},{"type":"text","text":"intelligent system 智能系统"},{"type":"entry","text":"invention /ɪnˈvenʃn/ n. 发明，创造，发明物","headword":"invention"},{"type":"note","text":"搭配 invention patent 发明专利"},{"type":"entry","text":"nanometer /ˈnænoʊmiːtər/ n. 纳米","headword":"nanometer"},{"type":"entry","text":"upgrade /ˌʌpˈɡreɪd/ vt. 升级","headword":"upgrade"},{"type":"note","text":"搭配 upgrade industry 产业升级"},{"type":"text","text":"wireless technology 无线科技"},{"type":"text","text":"3D printer 3D打印机"}]}]}